Workbook

Sheet datos_limpios
A1: id_producto | B1: categoria | C1: grupo | D1: producto | E1: precio_lista | F1: descuento_pct | G1: precio_venta | H1: ahorro_unitario | I1: cantidad_disponible | J1: agotado | K1: agotado_num | L1: nivel_stock | M1: valor_inventario | N1: ahorro_potencial | O1: peso_gramos | P1: cantidad_paquete | Q1: rango_precio | R1: rango_descuento | S1: n_categorias | T1: es_listado_principal
A2: P0001 | B2: Fruits & Vegetables | C2: Alimentos y bebidas | D2: Onion | E2: 25 | F2: 16 | G2: 21 | H2: =ROUND(E2-G2,2) -> 4 | I2: 3 | J2: =FALSE() -> FALSE | K2: =IF(J2,1,0) -> 0 | L2: Medio (3-5) | M2: =ROUND(G2*I2,2) -> 63 | N2: =ROUND(H2*I2,2) -> 12 | O2: 1000 | P2: 1 | Q2: 0-50 | R2: 11-20% | S2: 1 | T2: 1
A3: P0002 | B3: Fruits & Vegetables | C3: Alimentos y bebidas | D3: Tomato Hybrid | E3: 42 | F3: 16 | G3: 35 | H3: =ROUND(E3-G3,2) -> 7 | I3: 3 | J3: =FALSE() -> FALSE | K3: =IF(J3,1,0) -> 0 | L3: Medio (3-5) | M3: =ROUND(G3*I3,2) -> 105 | N3: =ROUND(H3*I3,2) -> 21 | O3: 1000 | P3: 1 | Q3: 0-50 | R3: 11-20% | S3: 1 | T3: 1
A4: P0003 | B4: Fruits & Vegetables | C4: Alimentos y bebidas | D4: Tender Coconut | E4: 51 | F4: 15 | G4: 43 | H4: =ROUND(E4-G4,2) -> 8 | I4: 3 | J4: =FALSE() -> FALSE | K4: =IF(J4,1,0) -> 0 | L4: Medio (3-5) | M4: =ROUND(G4*I4,2) -> 129 | N4: =ROUND(H4*I4,2) -> 24 | O4: 58 | P4: 1 | Q4: 51-100 | R4: 11-20% | S4: 1 | T4: 1
A5: P0004 | B5: Fruits & Vegetables | C5: Alimentos y bebidas | D5: Coriander Leaves | E5: 20 | F5: 15 | G5: 17 | H5: =ROUND(E5-G5,2) -> 3 | I5: 3 | J5: =FALSE() -> FALSE | K5: =IF(J5,1,0) -> 0 | L5: Medio (3-5) | M5: =ROUND(G5*I5,2) -> 51 | N5: =ROUND(H5*I5,2) -> 9 | O5: 100 | P5: 100 | Q5: 0-50 | R5: 11-20% | S5: 1 | T5: 1
A6: P0005 | B6: Fruits & Vegetables | C6: Alimentos y bebidas | D6: Ladies Finger | E6: 14 | F6: 14 | G6: 12 | H6: =ROUND(E6-G6,2) -> 2 | I6: 3 | J6: =FALSE() -> FALSE | K6: =IF(J6,1,0) -> 0 | L6: Medio (3-5) | M6: =ROUND(G6*I6,2) -> 36 | N6: =ROUND(H6*I6,2) -> 6 | O6: 250 | P6: 250 | Q6: 0-50 | R6: 11-20% | S6: 1 | T6: 1
A7: P0006 | B7: Fruits & Vegetables | C7: Alimentos y bebidas | D7: Potato | E7: 35 | F7: 17 | G7: 29 | H7: =ROUND(E7-G7,2) -> 6 | I7: 3 | J7: =FALSE() -> FALSE | K7: =IF(J7,1,0) -> 0 | L7: Medio (3-5) | M7: =ROUND(G7*I7,2) -> 87 | N7: =ROUND(H7*I7,2) -> 18 | O7: 1000 | P7: 1 | Q7: 0-50 | R7: 11-20% | S7: 1 | T7: 1
A8: P0007 | B8: Fruits & Vegetables | C8: Alimentos y bebidas | D8: Lemon | E8: 75 | F8: 16 | G8: 63 | H8: =ROUND(E8-G8,2) -> 12 | I8: 3 | J8: =FALSE() -> FALSE | K8: =IF(J8,1,0) -> 0 | L8: Medio (3-5) | M8: =ROUND(G8*I8,2) -> 189 | N8: =ROUND(H8*I8,2) -> 36 | O8: 200 | P8: 200 | Q8: 51-100 | R8: 11-20% | S8: 1 | T8: 1
A9: P0008 | B9: Fruits & Vegetables | C9: Alimentos y bebidas | D9: Watermelon | E9: 58 | F9: 15 | G9: 49 | H9: =ROUND(E9-G9,2) -> 9 | I9: 3 | J9: =FALSE() -> FALSE | K9: =IF(J9,1,0) -> 0 | L9: Medio (3-5) | M9: =ROUND(G9*I9,2) -> 147 | N9: =ROUND(H9*I9,2) -> 27 | O9: 58 | P9: 1 | Q9: 51-100 | R9: 11-20% | S9: 1 | T9: 1
A10: P0009 | B10: Fruits & Vegetables | C10: Alimentos y bebidas | D10: Capsicum Green | E10: 23 | F10: 17 | G10: 19 | H10: =ROUND(E10-G10,2) -> 4 | I10: 3 | J10: =FALSE() -> FALSE | K10: =IF(J10,1,0) -> 0 | L10: Medio (3-5) | M10: =ROUND(G10*I10,2) -> 57 | N10: =ROUND(H10*I10,2) -> 12 | O10: 250 | P10: 250 | Q10: 0-50 | R10: 11-20% | S10: 1 | T10: 1
A11: P0010 | B11: Fruits & Vegetables | C11: Alimentos y bebidas | D11: Chilli Green | E11: 19 | F11: 15 | G11: 16 | H11: =ROUND(E11-G11,2) -> 3 | I11: 3 | J11: =FALSE() -> FALSE | K11: =IF(J11,1,0) -> 0 | L11: Medio (3-5) | M11: =ROUND(G11*I11,2) -> 48 | N11: =ROUND(H11*I11,2) -> 9 | O11: 100 | P11: 100 | Q11: 0-50 | R11: 11-20% | S11: 1 | T11: 1
A12: P0011 | B12: Fruits & Vegetables | C12: Alimentos y bebidas | D12: Banana Robusta | E12: 29 | F12: 17 | G12: 24 | H12: =ROUND(E12-G12,2) -> 5 | I12: 3 | J12: =FALSE() -> FALSE | K12: =IF(J12,1,0) -> 0 | L12: Medio (3-5) | M12: =ROUND(G12*I12,2) -> 72 | N12: =ROUND(H12*I12,2) -> 15 | O12: 348 | P12: 6 | Q12: 0-50 | R12: 11-20% | S12: 1 | T12: 1
A13: P0012 | B13: Fruits & Vegetables | C13: Alimentos y bebidas | D13: Garlic Indian | E13: 11 | F13: 18 | G13: 9 | H13: =ROUND(E13-G13,2) -> 2 | I13: 3 | J13: =FALSE() -> FALSE | K13: =IF(J13,1,0) -> 0 | L13: Medio (3-5) | M13: =ROUND(G13*I13,2) -> 27 | N13: =ROUND(H13*I13,2) -> 6 | O13: 100 | P13: 100 | Q13: 0-50 | R13: 11-20% | S13: 1 | T13: 1
... A88: P0087 | B88: Fruits & Vegetables | C88: Alimentos y bebidas | D88: Garlic | E88: 17 | F88: 23 | G88: 13 | H88: =ROUND(E88-G88,2) -> 4 | I88: 3 | J88: =FALSE() -> FALSE | K88: =IF(J88,1,0) -> 0 | L88: Medio (3-5) | M88: =ROUND(G88*I88,2) -> 39 | N88: =ROUND(H88*I88,2) -> 12 | O88: 200 | P88: 200 | Q88: 0-50 | R88: 21% o mas | S88: 1 | T88: 1
A89: P0088 | B89: Fruits & Vegetables | C89: Alimentos y bebidas | D89: Carrot | E89: 13 | F89: 15 | G89: 11 | H89: =ROUND(E89-G89,2) -> 2 | I89: 0 | J89: =TRUE() -> TRUE | K89: =IF(J89,1,0) -> 1 | L89: Agotado | M89: =ROUND(G89*I89,2) -> 0 | N89: =ROUND(H89*I89,2) -> 0 | O89: 250 | P89: 200 | Q89: 0-50 | R89: 11-20% | S89: 1 | T89: 1
A90: P0089 | B90: Fruits & Vegetables | C90: Alimentos y bebidas | D90: Beetroot | E90: 11 | F90: 18 | G90: 9 | H90: =ROUND(E90-G90,2) -> 2 | I90: 0 | J90: =TRUE() -> TRUE | K90: =IF(J90,1,0) -> 1 | L90: Agotado | M90: =ROUND(G90*I90,2) -> 0 | N90: =ROUND(H90*I90,2) -> 0 | O90: 250 | P90: 250 | Q90: 0-50 | R90: 11-20% | S90: 1 | T90: 1
A91: P0090 | B91: Fruits & Vegetables | C91: Alimentos y bebidas | D91: Moong Sprouts | E91: 35 | F91: 17 | G91: 29 | H91: =ROUND(E91-G91,2) -> 6 | I91: 0 | J91: =TRUE() -> TRUE | K91: =IF(J91,1,0) -> 1 | L91: Agotado | M91: =ROUND(G91*I91,2) -> 0 | N91: =ROUND(H91*I91,2) -> 0 | O91: 200 | P91: 200 | Q91: 0-50 | R91: 11-20% | S91: 1 | T91: 1
A92: P0091 | B92: Fruits & Vegetables | C92: Alimentos y bebidas | D92: Safal Frozen Mixed Vegetables | E92: 60 | F92: 5 | G92: 57 | H92: =ROUND(E92-G92,2) -> 3 | I92: 0 | J92: =TRUE() -> TRUE | K92: =IF(J92,1,0) -> 1 | L92: Agotado | M92: =ROUND(G92*I92,2) -> 0 | N92: =ROUND(H92*I92,2) -> 0 | O92: 500 | P92: 500 | Q92: 51-100 | R92: 1-10% | S92: 4 | T92: 1
A93: P0092 | B93: Fruits & Vegetables | C93: Alimentos y bebidas | D93: Safal Frozen Corn | E93: 41 | F93: 4 | G93: 39 | H93: =ROUND(E93-G93,2) -> 2 | I93: 0 | J93: =TRUE() -> TRUE | K93: =IF(J93,1,0) -> 1 | L93: Agotado | M93: =ROUND(G93*I93,2) -> 0 | N93: =ROUND(H93*I93,2) -> 0 | O93: 200 | P93: 200 | Q93: 0-50 | R93: 1-10% | S93: 4 | T93: 1
A94: P0093 | B94: Fruits & Vegetables | C94: Alimentos y bebidas | D94: Safal Frozen - Sweet Corn | E94: 160 | F94: 5 | G94: 152 | H94: =ROUND(E94-G94,2) -> 8 | I94: 0 | J94: =TRUE() -> TRUE | K94: =IF(J94,1,0) -> 1 | L94: Agotado | M94: =ROUND(G94*I94,2) -> 0 | N94: =ROUND(H94*I94,2) -> 0 | O94: 1000 | P94: 1 | Q94: 101-200 | R94: 1-10% | S94: 4 | T94: 1
A95: P0094 | B95: Cooking Essentials | C95: Alimentos y bebidas | D95: Maggi 2 Minute Masala Noodles | E95: 12 | F95: 0 | G95: 12 | H95: =ROUND(E95-G95,2) -> 0 | I95: 6 | J95: =FALSE() -> FALSE | K95: =IF(J95,1,0) -> 0 | L95: Alto (6) | M95: =ROUND(G95*I95,2) -> 72 | N95: =ROUND(H95*I95,2) -> 0 | O95: 70 | P95: 70 | Q95: 0-50 | R95: Sin descuento | S95: 5 | T95: 1
A96: P0095 | B96: Cooking Essentials | C96: Alimentos y bebidas | D96: iD Idli & Dosa Batter | E96: 80 | F96: 15 | G96: 68 | H96: =ROUND(E96-G96,2) -> 12 | I96: 6 | J96: =FALSE() -> FALSE | K96: =IF(J96,1,0) -> 0 | L96: Alto (6) | M96: =ROUND(G96*I96,2) -> 408 | N96: =ROUND(H96*I96,2) -> 72 | O96: 1000 | P96: 1 | Q96: 51-100 | R96: 11-20% | S96: 7 | T96: 1
A97: P0096 | B97: Cooking Essentials | C97: Alimentos y bebidas | D97: Tata Salt | E97: 24 | F97: 0 | G97: 24 | H97: =ROUND(E97-G97,2) -> 0 | I97: 6 | J97: =FALSE() -> FALSE | K97: =IF(J97,1,0) -> 0 | L97: Alto (6) | M97: =ROUND(G97*I97,2) -> 144 | N97: =ROUND(H97*I97,2) -> 0 | O97: 1000 | P97: 1 | Q97: 0-50 | R97: Sin descuento | S97: 2 | T97: 1
A98: P0097 | B98: Cooking Essentials | C98: Alimentos y bebidas | D98: Arden Eggs White | E98: 97 | F98: 0 | G98: 97 | H98: =ROUND(E98-G98,2) -> 0 | I98: 4 | J98: =FALSE() -> FALSE | K98: =IF(J98,1,0) -> 0 | L98: Medio (3-5) | M98: =ROUND(G98*I98,2) -> 388 | N98: =ROUND(H98*I98,2) -> 0 | O98: 696 | P98: 12 | Q98: 51-100 | R98: Sin descuento | S98: 5 | T98: 1
A99: P0098 | B99: Cooking Essentials | C99: Alimentos y bebidas | D99: Arden Eggs White | E99: 65 | F99: 15 | G99: 55 | H99: =ROUND(E99-G99,2) -> 10 | I99: 4 | J99: =FALSE() -> FALSE | K99: =IF(J99,1,0) -> 0 | L99: Medio (3-5) | M99: =ROUND(G99*I99,2) -> 220 | N99: =ROUND(H99*I99,2) -> 40 | O99: 348 | P99: 6 | Q99: 51-100 | R99: 11-20% | S99: 5 | T99: 1
A100: P0099 | B100: Cooking Essentials | C100: Alimentos y bebidas | D100: Fortune Sunlite Refined Sunflower (Pouch) | E100: 230 | F100: 4 | G100: 219 | H100: =ROUND(E100-G100,2) -> 11 | I100: 6 | J100: =FALSE() -> FALSE | K100: =IF(J100,1,0) -> 0 | L100: Alto (6) | M100: =ROUND(G100*I100,2) -> 1314 | N100: =ROUND(H100*I100,2) -> 66 | O100: 1000 | P100: 1 | Q100: 201-500 | R100: 1-10% | S100: 2 | T100: 1
A101: P0100 | B101: Cooking Essentials | C101: Alimentos y bebidas | D101: Aashirvaad Superior MP Atta | E101: 250 | F101: 2 | G101: 245 | H101: =ROUND(E101-G101,2) -> 5 | I101: 6 | J101: =FALSE() -> FALSE | K101: =IF(J101,1,0) -> 0 | L101: Alto (6) | M101: =ROUND(G101*I101,2) -> 1470 | N101: =ROUND(H101*I101,2) -> 30 | O101: 5000 | P101: 5 | Q101: 201-500 | R101: 1-10% | S101: 2 | T101: 1
A102: P0101 | B102: Cooking Essentials | C102: Alimentos y bebidas | D102: Amul Pure Ghee (Pouch) | E102: 255 | F102: 2 | G102: 249 | H102: =ROUND(E102-G102,2) -> 6 | I102: 6 | J102: =FALSE() -> FALSE | K102: =IF(J102,1,0) -> 0 | L102: Alto (6) | M102: =ROUND(G102*I102,2) -> 1494 | N102: =ROUND(H102*I102,2) -> 36 | O102: 500 | P102: 500 | Q102: 201-500 | R102: 1-10% | S102: 2 | T102: 1
A103: P0102 | B103: Cooking Essentials | C103: Alimentos y bebidas | D103: Arden Eggs Brown | E103: 85 | F103: 7 | G103: 79 | H103: =ROUND(E103-G103,2) -> 6 | I103: 4 | J103: =FALSE() -> FALSE | K103: =IF(J103,1,0) -> 0 | L103: Medio (3-5) | M103: =ROUND(G103*I103,2) -> 316 | N103: =ROUND(H103*I103,2) -> 24 | O103: 348 | P103: 6 | Q103: 51-100 | R103: 1-10% | S103: 5 | T103: 1
A104: P0103 | B104: Cooking Essentials | C104: Alimentos y bebidas | D104: Tata Salt Lite | E104: 40 | F104: 10 | G104: 36 | H104: =ROUND(E104-G104,2) -> 4 | I104: 6 | J104: =FALSE() -> FALSE | K104: =IF(J104,1,0) -> 0 | L104: Alto (6) | M104: =ROUND(G104*I104,2) -> 216 | N104: =ROUND(H104*I104,2) -> 24 | O104: 1000 | P104: 1 | Q104: 0-50 | R104: 1-10% | S104: 2 | T104: 1
A105: P0104 | B105: Cooking Essentials | C105: Alimentos y bebidas | D105: Saffola Gold Oil (Pouch) | E105: 215 | F105: 0 | G105: 215 | H105: =ROUND(E105-G105,2) -> 0 | I105: 6 | J105: =FALSE() -> FALSE | K105: =IF(J105,1,0) -> 0 | L105: Alto (6) | M105: =ROUND(G105*I105,2) -> 1290 | N105: =ROUND(H105*I105,2) -> 0 | O105: 1000 | P105: 1 | Q105: 201-500 | R105: Sin descuento | S105: 2 | T105: 1
A106: P0105 | B106: Cooking Essentials | C106: Alimentos y bebidas | D106: Fortune Sunlite Refined Sunflower (Jar) | E106: 925 | F106: 0 | G106: 925 | H106: =ROUND(E106-G106,2) -> 0 | I106: 6 | J106: =FALSE() -> FALSE | K106: =IF(J106,1,0) -> 0 | L106: Alto (6) | M106: =ROUND(G106*I106,2) -> 5550 | N106: =ROUND(H106*I106,2) -> 0 | O106: 5000 | P106: 5 | Q106: 500+ | R106: Sin descuento | S106: 2 | T106: 1
... A544: P0543 | B544: Cooking Essentials | C544: Alimentos y bebidas | D544: Figaro Pure Olive Oil | E544: 325 | F544: 8 | G544: 299 | H544: =ROUND(E544-G544,2) -> 26 | I544: 1 | J544: =FALSE() -> FALSE | K544: =IF(J544,1,0) -> 0 | L544: Bajo (1-2) | M544: =ROUND(G544*I544,2) -> 299 | N544: =ROUND(H544*I544,2) -> 26 | O544: 200 | P544: 200 | Q544: 201-500 | R544: 1-10% | S544: 2 | T544: 1
A545: P0544 | B545: Cooking Essentials | C545: Alimentos y bebidas | D545: Madhur Sugar | E545: 60 | F545: 6 | G545: 56 | H545: =ROUND(E545-G545,2) -> 4 | I545: 0 | J545: =TRUE() -> TRUE | K545: =IF(J545,1,0) -> 1 | L545: Agotado | M545: =ROUND(G545*I545,2) -> 0 | N545: =ROUND(H545*I545,2) -> 0 | O545: 1000 | P545: 1 | Q545: 51-100 | R545: 1-10% | S545: 2 | T545: 1
A546: P0545 | B546: Cooking Essentials | C546: Alimentos y bebidas | D546: Amul Fresh Cream | E546: 63 | F546: 0 | G546: 63 | H546: =ROUND(E546-G546,2) -> 0 | I546: 0 | J546: =TRUE() -> TRUE | K546: =IF(J546,1,0) -> 1 | L546: Agotado | M546: =ROUND(G546*I546,2) -> 0 | N546: =ROUND(H546*I546,2) -> 0 | O546: 250 | P546: 250 | Q546: 51-100 | R546: Sin descuento | S546: 4 | T546: 1
A547: P0546 | B547: Cooking Essentials | C547: Alimentos y bebidas | D547: Madhur Pure And Hygienic Sugar | E547: 295 | F547: 9 | G547: 266 | H547: =ROUND(E547-G547,2) -> 29 | I547: 0 | J547: =TRUE() -> TRUE | K547: =IF(J547,1,0) -> 1 | L547: Agotado | M547: =ROUND(G547*I547,2) -> 0 | N547: =ROUND(H547*I547,2) -> 0 | O547: 5000 | P547: 5 | Q547: 201-500 | R547: 1-10% | S547: 2 | T547: 1
A548: P0547 | B548: Cooking Essentials | C548: Alimentos y bebidas | D548: Satyam Poha Jada | E548: 35 | F548: 8 | G548: 32 | H548: =ROUND(E548-G548,2) -> 3 | I548: 0 | J548: =TRUE() -> TRUE | K548: =IF(J548,1,0) -> 1 | L548: Agotado | M548: =ROUND(G548*I548,2) -> 0 | N548: =ROUND(H548*I548,2) -> 0 | O548: 500 | P548: 500 | Q548: 0-50 | R548: 1-10% | S548: 2 | T548: 1
A549: P0548 | B549: Cooking Essentials | C549: Alimentos y bebidas | D549: Aashirvaad Superior MP Whole Wheat Atta | E549: 53 | F549: 1 | G549: 52 | H549: =ROUND(E549-G549,2) -> 1 | I549: 0 | J549: =TRUE() -> TRUE | K549: =IF(J549,1,0) -> 1 | L549: Agotado | M549: =ROUND(G549*I549,2) -> 0 | N549: =ROUND(H549*I549,2) -> 0 | O549: 1000 | P549: 1 | Q549: 51-100 | R549: 1-10% | S549: 2 | T549: 1
A550: P0549 | B550: Cooking Essentials | C550: Alimentos y bebidas | D550: Fortune Soyabean Oil | E550: 210 | F550: 13 | G550: 181 | H550: =ROUND(E550-G550,2) -> 29 | I550: 0 | J550: =TRUE() -> TRUE | K550: =IF(J550,1,0) -> 1 | L550: Agotado | M550: =ROUND(G550*I550,2) -> 0 | N550: =ROUND(H550*I550,2) -> 0 | O550: 1000 | P550: 1 | Q550: 201-500 | R550: 11-20% | S550: 2 | T550: 1
A551: P0550 | B551: Cooking Essentials | C551: Alimentos y bebidas | D551: Maggi Masala Ae Magic | E551: 58 | F551: 6 | G551: 54 | H551: =ROUND(E551-G551,2) -> 4 | I551: 0 | J551: =TRUE() -> TRUE | K551: =IF(J551,1,0) -> 1 | L551: Agotado | M551: =ROUND(G551*I551,2) -> 0 | N551: =ROUND(H551*I551,2) -> 0 | O551: 72 | P551: 72 | Q551: 51-100 | R551: 1-10% | S551: 2 | T551: 1
A552: P0551 | B552: Cooking Essentials | C552: Alimentos y bebidas | D552: Aashirvaad Iodised Salt | E552: 22 | F552: 13 | G552: 19 | H552: =ROUND(E552-G552,2) -> 3 | I552: 0 | J552: =TRUE() -> TRUE | K552: =IF(J552,1,0) -> 1 | L552: Agotado | M552: =ROUND(G552*I552,2) -> 0 | N552: =ROUND(H552*I552,2) -> 0 | O552: 1000 | P552: 1 | Q552: 0-50 | R552: 11-20% | S552: 2 | T552: 1
A553: P0552 | B553: Cooking Essentials | C553: Alimentos y bebidas | D553: Maggi 2-Minute Instant Noodles - Masala | E553: 44 | F553: 0 | G553: 44 | H553: =ROUND(E553-G553,2) -> 0 | I553: 0 | J553: =TRUE() -> TRUE | K553: =IF(J553,1,0) -> 1 | L553: Agotado | M553: =ROUND(G553*I553,2) -> 0 | N553: =ROUND(H553*I553,2) -> 0 | O553: 280 | P553: 280 | Q553: 0-50 | R553: Sin descuento | S553: 5 | T553: 1
A554: P0553 | B554: Cooking Essentials | C554: Alimentos y bebidas | D554: Popular Essentials Phool Makhana (Jumbo Size) | E554: 150 | F554: 14 | G554: 128 | H554: =ROUND(E554-G554,2) -> 22 | I554: 0 | J554: =TRUE() -> TRUE | K554: =IF(J554,1,0) -> 1 | L554: Agotado | M554: =ROUND(G554*I554,2) -> 0 | N554: =ROUND(H554*I554,2) -> 0 | O554: 100 | P554: 100 | Q554: 101-200 | R554: 11-20% | S554: 2 | T554: 1
A555: P0554 | B555: Cooking Essentials | C555: Alimentos y bebidas | D555: Aashirvaad Atta With Mutigrains | E555: 315 | F555: 8 | G555: 287 | H555: =ROUND(E555-G555,2) -> 28 | I555: 0 | J555: =TRUE() -> TRUE | K555: =IF(J555,1,0) -> 1 | L555: Agotado | M555: =ROUND(G555*I555,2) -> 0 | N555: =ROUND(H555*I555,2) -> 0 | O555: 5000 | P555: 5 | Q555: 201-500 | R555: 1-10% | S555: 2 | T555: 1
A556: P0555 | B556: Cooking Essentials | C556: Alimentos y bebidas | D556: Tata Sampann Poha | E556: 44 | F556: 6 | G556: 41 | H556: =ROUND(E556-G556,2) -> 3 | I556: 0 | J556: =TRUE() -> TRUE | K556: =IF(J556,1,0) -> 1 | L556: Agotado | M556: =ROUND(G556*I556,2) -> 0 | N556: =ROUND(H556*I556,2) -> 0 | O556: 500 | P556: 500 | Q556: 0-50 | R556: 1-10% | S556: 2 | T556: 1
... A607: P0606 | B607: Cooking Essentials | C607: Alimentos y bebidas | D607: Godrej Yummiez Chicken Breakfast Salami | E607: 150 | F607: 4 | G607: 143 | H607: =ROUND(E607-G607,2) -> 7 | I607: 0 | J607: =TRUE() -> TRUE | K607: =IF(J607,1,0) -> 1 | L607: Agotado | M607: =ROUND(G607*I607,2) -> 0 | N607: =ROUND(H607*I607,2) -> 0 | O607: 250 | P607: 250 | Q607: 101-200 | R607: 1-10% | S607: 6 | T607: 1
A608: P0607 | B608: Cooking Essentials | C608: Alimentos y bebidas | D608: Everest Saffron Kesar | E608: 120 | F608: 0 | G608: 120 | H608: =ROUND(E608-G608,2) -> 0 | I608: 0 | J608: =TRUE() -> TRUE | K608: =IF(J608,1,0) -> 1 | L608: Agotado | M608: =ROUND(G608*I608,2) -> 0 | N608: =ROUND(H608*I608,2) -> 0 | O608: 1 | Q608: 101-200 | R608: Sin descuento | S608: 2 | T608: 1
A609: P0094 | B609: Munchies | C609: Alimentos y bebidas | D609: Maggi 2 Minute Masala Noodles | E609: 12 | F609: 0 | G609: 12 | H609: =ROUND(E609-G609,2) -> 0 | I609: 6 | J609: =FALSE() -> FALSE | K609: =IF(J609,1,0) -> 0 | L609: Alto (6) | M609: =ROUND(G609*I609,2) -> 72 | N609: =ROUND(H609*I609,2) -> 0 | O609: 70 | P609: 70 | Q609: 0-50 | R609: Sin descuento | S609: 5 | T609: 0
A610: P0095 | B610: Munchies | C610: Alimentos y bebidas | D610: iD Idli & Dosa Batter | E610: 80 | F610: 15 | G610: 68 | H610: =ROUND(E610-G610,2) -> 12 | I610: 6 | J610: =FALSE() -> FALSE | K610: =IF(J610,1,0) -> 0 | L610: Alto (6) | M610: =ROUND(G610*I610,2) -> 408 | N610: =ROUND(H610*I610,2) -> 72 | O610: 1000 | P610: 1 | Q610: 51-100 | R610: 11-20% | S610: 7 | T610: 0
A611: P0096 | B611: Munchies | C611: Alimentos y bebidas | D611: Tata Salt | E611: 24 | F611: 0 | G611: 24 | H611: =ROUND(E611-G611,2) -> 0 | I611: 6 | J611: =FALSE() -> FALSE | K611: =IF(J611,1,0) -> 0 | L611: Alto (6) | M611: =ROUND(G611*I611,2) -> 144 | N611: =ROUND(H611*I611,2) -> 0 | O611: 1000 | P611: 1 | Q611: 0-50 | R611: Sin descuento | S611: 2 | T611: 0
A612: P0097 | B612: Munchies | C612: Alimentos y bebidas | D612: Arden Eggs White | E612: 97 | F612: 0 | G612: 97 | H612: =ROUND(E612-G612,2) -> 0 | I612: 4 | J612: =FALSE() -> FALSE | K612: =IF(J612,1,0) -> 0 | L612: Medio (3-5) | M612: =ROUND(G612*I612,2) -> 388 | N612: =ROUND(H612*I612,2) -> 0 | O612: 696 | P612: 12 | Q612: 51-100 | R612: Sin descuento | S612: 5 | T612: 0
A613: P0098 | B613: Munchies | C613: Alimentos y bebidas | D613: Arden Eggs White | E613: 65 | F613: 15 | G613: 55 | H613: =ROUND(E613-G613,2) -> 10 | I613: 4 | J613: =FALSE() -> FALSE | K613: =IF(J613,1,0) -> 0 | L613: Medio (3-5) | M613: =ROUND(G613*I613,2) -> 220 | N613: =ROUND(H613*I613,2) -> 40 | O613: 348 | P613: 6 | Q613: 51-100 | R613: 11-20% | S613: 5 | T613: 0
A614: P0099 | B614: Munchies | C614: Alimentos y bebidas | D614: Fortune Sunlite Refined Sunflower (Pouch) | E614: 230 | F614: 4 | G614: 219 | H614: =ROUND(E614-G614,2) -> 11 | I614: 6 | J614: =FALSE() -> FALSE | K614: =IF(J614,1,0) -> 0 | L614: Alto (6) | M614: =ROUND(G614*I614,2) -> 1314 | N614: =ROUND(H614*I614,2) -> 66 | O614: 1000 | P614: 1 | Q614: 201-500 | R614: 1-10% | S614: 2 | T614: 0
A615: P0100 | B615: Munchies | C615: Alimentos y bebidas | D615: Aashirvaad Superior MP Atta | E615: 250 | F615: 2 | G615: 245 | H615: =ROUND(E615-G615,2) -> 5 | I615: 6 | J615: =FALSE() -> FALSE | K615: =IF(J615,1,0) -> 0 | L615: Alto (6) | M615: =ROUND(G615*I615,2) -> 1470 | N615: =ROUND(H615*I615,2) -> 30 | O615: 5000 | P615: 5 | Q615: 201-500 | R615: 1-10% | S615: 2 | T615: 0
A616: P0101 | B616: Munchies | C616: Alimentos y bebidas | D616: Amul Pure Ghee (Pouch) | E616: 255 | F616: 2 | G616: 249 | H616: =ROUND(E616-G616,2) -> 6 | I616: 6 | J616: =FALSE() -> FALSE | K616: =IF(J616,1,0) -> 0 | L616: Alto (6) | M616: =ROUND(G616*I616,2) -> 1494 | N616: =ROUND(H616*I616,2) -> 36 | O616: 500 | P616: 500 | Q616: 201-500 | R616: 1-10% | S616: 2 | T616: 0
A617: P0102 | B617: Munchies | C617: Alimentos y bebidas | D617: Arden Eggs Brown | E617: 85 | F617: 7 | G617: 79 | H617: =ROUND(E617-G617,2) -> 6 | I617: 4 | J617: =FALSE() -> FALSE | K617: =IF(J617,1,0) -> 0 | L617: Medio (3-5) | M617: =ROUND(G617*I617,2) -> 316 | N617: =ROUND(H617*I617,2) -> 24 | O617: 348 | P617: 6 | Q617: 51-100 | R617: 1-10% | S617: 5 | T617: 0
A618: P0103 | B618: Munchies | C618: Alimentos y bebidas | D618: Tata Salt Lite | E618: 40 | F618: 10 | G618: 36 | H618: =ROUND(E618-G618,2) -> 4 | I618: 6 | J618: =FALSE() -> FALSE | K618: =IF(J618,1,0) -> 0 | L618: Alto (6) | M618: =ROUND(G618*I618,2) -> 216 | N618: =ROUND(H618*I618,2) -> 24 | O618: 1000 | P618: 1 | Q618: 0-50 | R618: 1-10% | S618: 2 | T618: 0
A619: P0104 | B619: Munchies | C619: Alimentos y bebidas | D619: Saffola Gold Oil (Pouch) | E619: 215 | F619: 0 | G619: 215 | H619: =ROUND(E619-G619,2) -> 0 | I619: 6 | J619: =FALSE() -> FALSE | K619: =IF(J619,1,0) -> 0 | L619: Alto (6) | M619: =ROUND(G619*I619,2) -> 1290 | N619: =ROUND(H619*I619,2) -> 0 | O619: 1000 | P619: 1 | Q619: 201-500 | R619: Sin descuento | S619: 2 | T619: 0
A620: P0105 | B620: Munchies | C620: Alimentos y bebidas | D620: Fortune Sunlite Refined Sunflower (Jar) | E620: 925 | F620: 0 | G620: 925 | H620: =ROUND(E620-G620,2) -> 0 | I620: 6 | J620: =FALSE() -> FALSE | K620: =IF(J620,1,0) -> 0 | L620: Alto (6) | M620: =ROUND(G620*I620,2) -> 5550 | N620: =ROUND(H620*I620,2) -> 0 | O620: 5000 | P620: 5 | Q620: 500+ | R620: Sin descuento | S620: 2 | T620: 0
... A1058: P0543 | B1058: Munchies | C1058: Alimentos y bebidas | D1058: Figaro Pure Olive Oil | E1058: 325 | F1058: 8 | G1058: 299 | H1058: =ROUND(E1058-G1058,2) -> 26 | I1058: 1 | J1058: =FALSE() -> FALSE | K1058: =IF(J1058,1,0) -> 0 | L1058: Bajo (1-2) | M1058: =ROUND(G1058*I1058,2) -> 299 | N1058: =ROUND(H1058*I1058,2) -> 26 | O1058: 200 | P1058: 200 | Q1058: 201-500 | R1058: 1-10% | S1058: 2 | T1058: 0
A1059: P0544 | B1059: Munchies | C1059: Alimentos y bebidas | D1059: Madhur Sugar | E1059: 60 | F1059: 6 | G1059: 56 | H1059: =ROUND(E1059-G1059,2) -> 4 | I1059: 0 | J1059: =TRUE() -> TRUE | K1059: =IF(J1059,1,0) -> 1 | L1059: Agotado | M1059: =ROUND(G1059*I1059,2) -> 0 | N1059: =ROUND(H1059*I1059,2) -> 0 | O1059: 1000 | P1059: 1 | Q1059: 51-100 | R1059: 1-10% | S1059: 2 | T1059: 0
A1060: P0545 | B1060: Munchies | C1060: Alimentos y bebidas | D1060: Amul Fresh Cream | E1060: 63 | F1060: 0 | G1060: 63 | H1060: =ROUND(E1060-G1060,2) -> 0 | I1060: 0 | J1060: =TRUE() -> TRUE | K1060: =IF(J1060,1,0) -> 1 | L1060: Agotado | M1060: =ROUND(G1060*I1060,2) -> 0 | N1060: =ROUND(H1060*I1060,2) -> 0 | O1060: 250 | P1060: 250 | Q1060: 51-100 | R1060: Sin descuento | S1060: 4 | T1060: 0
A1061: P0546 | B1061: Munchies | C1061: Alimentos y bebidas | D1061: Madhur Pure And Hygienic Sugar | E1061: 295 | F1061: 9 | G1061: 266 | H1061: =ROUND(E1061-G1061,2) -> 29 | I1061: 0 | J1061: =TRUE() -> TRUE | K1061: =IF(J1061,1,0) -> 1 | L1061: Agotado | M1061: =ROUND(G1061*I1061,2) -> 0 | N1061: =ROUND(H1061*I1061,2) -> 0 | O1061: 5000 | P1061: 5 | Q1061: 201-500 | R1061: 1-10% | S1061: 2 | T1061: 0
A1062: P0547 | B1062: Munchies | C1062: Alimentos y bebidas | D1062: Satyam Poha Jada | E1062: 35 | F1062: 8 | G1062: 32 | H1062: =ROUND(E1062-G1062,2) -> 3 | I1062: 0 | J1062: =TRUE() -> TRUE | K1062: =IF(J1062,1,0) -> 1 | L1062: Agotado | M1062: =ROUND(G1062*I1062,2) -> 0 | N1062: =ROUND(H1062*I1062,2) -> 0 | O1062: 500 | P1062: 500 | Q1062: 0-50 | R1062: 1-10% | S1062: 2 | T1062: 0
A1063: P0548 | B1063: Munchies | C1063: Alimentos y bebidas | D1063: Aashirvaad Superior MP Whole Wheat Atta | E1063: 53 | F1063: 1 | G1063: 52 | H1063: =ROUND(E1063-G1063,2) -> 1 | I1063: 0 | J1063: =TRUE() -> TRUE | K1063: =IF(J1063,1,0) -> 1 | L1063: Agotado | M1063: =ROUND(G1063*I1063,2) -> 0 | N1063: =ROUND(H1063*I1063,2) -> 0 | O1063: 1000 | P1063: 1 | Q1063: 51-100 | R1063: 1-10% | S1063: 2 | T1063: 0
A1064: P0549 | B1064: Munchies | C1064: Alimentos y bebidas | D1064: Fortune Soyabean Oil | E1064: 210 | F1064: 13 | G1064: 181 | H1064: =ROUND(E1064-G1064,2) -> 29 | I1064: 0 | J1064: =TRUE() -> TRUE | K1064: =IF(J1064,1,0) -> 1 | L1064: Agotado | M1064: =ROUND(G1064*I1064,2) -> 0 | N1064: =ROUND(H1064*I1064,2) -> 0 | O1064: 1000 | P1064: 1 | Q1064: 201-500 | R1064: 11-20% | S1064: 2 | T1064: 0
A1065: P0550 | B1065: Munchies | C1065: Alimentos y bebidas | D1065: Maggi Masala Ae Magic | E1065: 58 | F1065: 6 | G1065: 54 | H1065: =ROUND(E1065-G1065,2) -> 4 | I1065: 0 | J1065: =TRUE() -> TRUE | K1065: =IF(J1065,1,0) -> 1 | L1065: Agotado | M1065: =ROUND(G1065*I1065,2) -> 0 | N1065: =ROUND(H1065*I1065,2) -> 0 | O1065: 72 | P1065: 72 | Q1065: 51-100 | R1065: 1-10% | S1065: 2 | T1065: 0
A1066: P0551 | B1066: Munchies | C1066: Alimentos y bebidas | D1066: Aashirvaad Iodised Salt | E1066: 22 | F1066: 13 | G1066: 19 | H1066: =ROUND(E1066-G1066,2) -> 3 | I1066: 0 | J1066: =TRUE() -> TRUE | K1066: =IF(J1066,1,0) -> 1 | L1066: Agotado | M1066: =ROUND(G1066*I1066,2) -> 0 | N1066: =ROUND(H1066*I1066,2) -> 0 | O1066: 1000 | P1066: 1 | Q1066: 0-50 | R1066: 11-20% | S1066: 2 | T1066: 0
A1067: P0552 | B1067: Munchies | C1067: Alimentos y bebidas | D1067: Maggi 2-Minute Instant Noodles - Masala | E1067: 44 | F1067: 0 | G1067: 44 | H1067: =ROUND(E1067-G1067,2) -> 0 | I1067: 0 | J1067: =TRUE() -> TRUE | K1067: =IF(J1067,1,0) -> 1 | L1067: Agotado | M1067: =ROUND(G1067*I1067,2) -> 0 | N1067: =ROUND(H1067*I1067,2) -> 0 | O1067: 280 | P1067: 280 | Q1067: 0-50 | R1067: Sin descuento | S1067: 5 | T1067: 0
A1068: P0553 | B1068: Munchies | C1068: Alimentos y bebidas | D1068: Popular Essentials Phool Makhana (Jumbo Size) | E1068: 150 | F1068: 14 | G1068: 128 | H1068: =ROUND(E1068-G1068,2) -> 22 | I1068: 0 | J1068: =TRUE() -> TRUE | K1068: =IF(J1068,1,0) -> 1 | L1068: Agotado | M1068: =ROUND(G1068*I1068,2) -> 0 | N1068: =ROUND(H1068*I1068,2) -> 0 | O1068: 100 | P1068: 100 | Q1068: 101-200 | R1068: 11-20% | S1068: 2 | T1068: 0
A1069: P0554 | B1069: Munchies | C1069: Alimentos y bebidas | D1069: Aashirvaad Atta With Mutigrains | E1069: 315 | F1069: 8 | G1069: 287 | H1069: =ROUND(E1069-G1069,2) -> 28 | I1069: 0 | J1069: =TRUE() -> TRUE | K1069: =IF(J1069,1,0) -> 1 | L1069: Agotado | M1069: =ROUND(G1069*I1069,2) -> 0 | N1069: =ROUND(H1069*I1069,2) -> 0 | O1069: 5000 | P1069: 5 | Q1069: 201-500 | R1069: 1-10% | S1069: 2 | T1069: 0
A1070: P0555 | B1070: Munchies | C1070: Alimentos y bebidas | D1070: Tata Sampann Poha | E1070: 44 | F1070: 6 | G1070: 41 | H1070: =ROUND(E1070-G1070,2) -> 3 | I1070: 0 | J1070: =TRUE() -> TRUE | K1070: =IF(J1070,1,0) -> 1 | L1070: Agotado | M1070: =ROUND(G1070*I1070,2) -> 0 | N1070: =ROUND(H1070*I1070,2) -> 0 | O1070: 500 | P1070: 500 | Q1070: 0-50 | R1070: 1-10% | S1070: 2 | T1070: 0
... A1121: P0606 | B1121: Munchies | C1121: Alimentos y bebidas | D1121: Godrej Yummiez Chicken Breakfast Salami | E1121: 150 | F1121: 4 | G1121: 143 | H1121: =ROUND(E1121-G1121,2) -> 7 | I1121: 0 | J1121: =TRUE() -> TRUE | K1121: =IF(J1121,1,0) -> 1 | L1121: Agotado | M1121: =ROUND(G1121*I1121,2) -> 0 | N1121: =ROUND(H1121*I1121,2) -> 0 | O1121: 250 | P1121: 250 | Q1121: 101-200 | R1121: 1-10% | S1121: 6 | T1121: 0
A1122: P0607 | B1122: Munchies | C1122: Alimentos y bebidas | D1122: Everest Saffron Kesar | E1122: 120 | F1122: 0 | G1122: 120 | H1122: =ROUND(E1122-G1122,2) -> 0 | I1122: 0 | J1122: =TRUE() -> TRUE | K1122: =IF(J1122,1,0) -> 1 | L1122: Agotado | M1122: =ROUND(G1122*I1122,2) -> 0 | N1122: =ROUND(H1122*I1122,2) -> 0 | O1122: 1 | Q1122: 101-200 | R1122: Sin descuento | S1122: 2 | T1122: 0
A1123: P0608 | B1123: Dairy, Bread & Batter | C1123: Alimentos y bebidas | D1123: Mother Dairy Toned Milk Pouch | E1123: 25 | F1123: 0 | G1123: 25 | H1123: =ROUND(E1123-G1123,2) -> 0 | I1123: 4 | J1123: =FALSE() -> FALSE | K1123: =IF(J1123,1,0) -> 0 | L1123: Medio (3-5) | M1123: =ROUND(G1123*I1123,2) -> 100 | N1123: =ROUND(H1123*I1123,2) -> 0 | O1123: 500 | P1123: 500 | Q1123: 0-50 | R1123: Sin descuento | S1123: 2 | T1123: 1
A1124: P0609 | B1124: Dairy, Bread & Batter | C1124: Alimentos y bebidas | D1124: Mother Dairy Classic Curd | E1124: 30 | F1124: 3 | G1124: 29 | H1124: =ROUND(E1124-G1124,2) -> 1 | I1124: 6 | J1124: =FALSE() -> FALSE | K1124: =IF(J1124,1,0) -> 0 | L1124: Alto (6) | M1124: =ROUND(G1124*I1124,2) -> 174 | N1124: =ROUND(H1124*I1124,2) -> 6 | O1124: 400 | P1124: 400 | Q1124: 0-50 | R1124: 1-10% | S1124: 2 | T1124: 1
A1125: P0610 | B1125: Dairy, Bread & Batter | C1125: Alimentos y bebidas | D1125: Mother Dairy Ultra Full Cream Milk | E1125: 31 | F1125: 0 | G1125: 31 | H1125: =ROUND(E1125-G1125,2) -> 0 | I1125: 4 | J1125: =FALSE() -> FALSE | K1125: =IF(J1125,1,0) -> 0 | L1125: Medio (3-5) | M1125: =ROUND(G1125*I1125,2) -> 124 | N1125: =ROUND(H1125*I1125,2) -> 0 | O1125: 500 | P1125: 500 | Q1125: 0-50 | R1125: Sin descuento | S1125: 2 | T1125: 1
A1126: P0611 | B1126: Dairy, Bread & Batter | C1126: Alimentos y bebidas | D1126: Amul Butter - Pasteurised | E1126: 50 | F1126: 2 | G1126: 49 | H1126: =ROUND(E1126-G1126,2) -> 1 | I1126: 6 | J1126: =FALSE() -> FALSE | K1126: =IF(J1126,1,0) -> 0 | L1126: Alto (6) | M1126: =ROUND(G1126*I1126,2) -> 294 | N1126: =ROUND(H1126*I1126,2) -> 6 | O1126: 100 | P1126: 100 | Q1126: 0-50 | R1126: 1-10% | S1126: 2 | T1126: 1
A1127: P0612 | B1127: Dairy, Bread & Batter | C1127: Alimentos y bebidas | D1127: Britannia Sandwich White Bread | E1127: 33 | F1127: 0 | G1127: 33 | H1127: =ROUND(E1127-G1127,2) -> 0 | I1127: 4 | J1127: =FALSE() -> FALSE | K1127: =IF(J1127,1,0) -> 0 | L1127: Medio (3-5) | M1127: =ROUND(G1127*I1127,2) -> 132 | N1127: =ROUND(H1127*I1127,2) -> 0 | O1127: 350 | P1127: 350 | Q1127: 0-50 | R1127: Sin descuento | S1127: 2 | T1127: 1
A1128: P0613 | B1128: Dairy, Bread & Batter | C1128: Alimentos y bebidas | D1128: iD Curd Pouch | E1128: 35 | F1128: 2 | G1128: 34 | H1128: =ROUND(E1128-G1128,2) -> 1 | I1128: 6 | J1128: =FALSE() -> FALSE | K1128: =IF(J1128,1,0) -> 0 | L1128: Alto (6) | M1128: =ROUND(G1128*I1128,2) -> 204 | N1128: =ROUND(H1128*I1128,2) -> 6 | O1128: 400 | P1128: 400 | Q1128: 0-50 | R1128: 1-10% | S1128: 2 | T1128: 1
A1129: P0095 | B1129: Dairy, Bread & Batter | C1129: Alimentos y bebidas | D1129: iD Idli & Dosa Batter | E1129: 80 | F1129: 15 | G1129: 68 | H1129: =ROUND(E1129-G1129,2) -> 12 | I1129: 6 | J1129: =FALSE() -> FALSE | K1129: =IF(J1129,1,0) -> 0 | L1129: Alto (6) | M1129: =ROUND(G1129*I1129,2) -> 408 | N1129: =ROUND(H1129*I1129,2) -> 72 | O1129: 1000 | P1129: 1 | Q1129: 51-100 | R1129: 11-20% | S1129: 7 | T1129: 0
A1130: P0614 | B1130: Dairy, Bread & Batter | C1130: Alimentos y bebidas | D1130: Britannia 100% Whole Wheat Bread | E1130: 45 | F1130: 0 | G1130: 45 | H1130: =ROUND(E1130-G1130,2) -> 0 | I1130: 4 | J1130: =FALSE() -> FALSE | K1130: =IF(J1130,1,0) -> 0 | L1130: Medio (3-5) | M1130: =ROUND(G1130*I1130,2) -> 180 | N1130: =ROUND(H1130*I1130,2) -> 0 | O1130: 450 | P1130: 450 | Q1130: 0-50 | R1130: Sin descuento | S1130: 2 | T1130: 1
A1131: P0615 | B1131: Dairy, Bread & Batter | C1131: Alimentos y bebidas | D1131: Britannia Healthy Slice Sandwich Bread | E1131: 40 | F1131: 0 | G1131: 40 | H1131: =ROUND(E1131-G1131,2) -> 0 | I1131: 4 | J1131: =FALSE() -> FALSE | K1131: =IF(J1131,1,0) -> 0 | L1131: Medio (3-5) | M1131: =ROUND(G1131*I1131,2) -> 160 | N1131: =ROUND(H1131*I1131,2) -> 0 | O1131: 450 | P1131: 450 | Q1131: 0-50 | R1131: Sin descuento | S1131: 2 | T1131: 1
A1132: P0616 | B1132: Dairy, Bread & Batter | C1132: Alimentos y bebidas | D1132: Gowardhan Classic Block Fresh Paneer | E1132: 89 | F1132: 8 | G1132: 81 | H1132: =ROUND(E1132-G1132,2) -> 8 | I1132: 6 | J1132: =FALSE() -> FALSE | K1132: =IF(J1132,1,0) -> 0 | L1132: Alto (6) | M1132: =ROUND(G1132*I1132,2) -> 486 | N1132: =ROUND(H1132*I1132,2) -> 48 | O1132: 200 | P1132: 200 | Q1132: 51-100 | R1132: 1-10% | S1132: 2 | T1132: 1
A1133: P0617 | B1133: Dairy, Bread & Batter | C1133: Alimentos y bebidas | D1133: Amul Processed Cheese Cubes | E1133: 106 | F1133: 4 | G1133: 101 | H1133: =ROUND(E1133-G1133,2) -> 5 | I1133: 6 | J1133: =FALSE() -> FALSE | K1133: =IF(J1133,1,0) -> 0 | L1133: Alto (6) | M1133: =ROUND(G1133*I1133,2) -> 606 | N1133: =ROUND(H1133*I1133,2) -> 30 | O1133: 200 | P1133: 200 | Q1133: 101-200 | R1133: 1-10% | S1133: 2 | T1133: 1
A1134: P0618 | B1134: Dairy, Bread & Batter | C1134: Alimentos y bebidas | D1134: Britannia Pav | E1134: 22 | F1134: 0 | G1134: 22 | H1134: =ROUND(E1134-G1134,2) -> 0 | I1134: 4 | J1134: =FALSE() -> FALSE | K1134: =IF(J1134,1,0) -> 0 | L1134: Medio (3-5) | M1134: =ROUND(G1134*I1134,2) -> 88 | N1134: =ROUND(H1134*I1134,2) -> 0 | O1134: 250 | P1134: 250 | Q1134: 0-50 | R1134: Sin descuento | S1134: 2 | T1134: 1
... A1223: P0693 | B1223: Dairy, Bread & Batter | C1223: Alimentos y bebidas | D1223: The Laughing Cow Cheese Spread Plain | E1223: 110 | F1223: 0 | G1223: 110 | H1223: =ROUND(E1223-G1223,2) -> 0 | I1223: 6 | J1223: =FALSE() -> FALSE | K1223: =IF(J1223,1,0) -> 0 | L1223: Alto (6) | M1223: =ROUND(G1223*I1223,2) -> 660 | N1223: =ROUND(H1223*I1223,2) -> 0 | O1223: 180 | P1223: 180 | Q1223: 101-200 | R1223: Sin descuento | S1223: 5 | T1223: 1
A1224: P0694 | B1224: Dairy, Bread & Batter | C1224: Alimentos y bebidas | D1224: Amul Malai Paneer Fresh | E1224: 76 | F1224: 3 | G1224: 73 | H1224: =ROUND(E1224-G1224,2) -> 3 | I1224: 0 | J1224: =TRUE() -> TRUE | K1224: =IF(J1224,1,0) -> 1 | L1224: Agotado | M1224: =ROUND(G1224*I1224,2) -> 0 | N1224: =ROUND(H1224*I1224,2) -> 0 | O1224: 200 | P1224: 200 | Q1224: 51-100 | R1224: 1-10% | S1224: 2 | T1224: 1
A1225: P0695 | B1225: Dairy, Bread & Batter | C1225: Alimentos y bebidas | D1225: Amul Taaza Toned Homogenised Milk | E1225: 66 | F1225: 3 | G1225: 64 | H1225: =ROUND(E1225-G1225,2) -> 2 | I1225: 0 | J1225: =TRUE() -> TRUE | K1225: =IF(J1225,1,0) -> 1 | L1225: Agotado | M1225: =ROUND(G1225*I1225,2) -> 0 | N1225: =ROUND(H1225*I1225,2) -> 0 | O1225: 1000 | P1225: 1 | Q1225: 51-100 | R1225: 1-10% | S1225: 2 | T1225: 1
A1226: P0545 | B1226: Dairy, Bread & Batter | C1226: Alimentos y bebidas | D1226: Amul Fresh Cream | E1226: 63 | F1226: 0 | G1226: 63 | H1226: =ROUND(E1226-G1226,2) -> 0 | I1226: 0 | J1226: =TRUE() -> TRUE | K1226: =IF(J1226,1,0) -> 1 | L1226: Agotado | M1226: =ROUND(G1226*I1226,2) -> 0 | N1226: =ROUND(H1226*I1226,2) -> 0 | O1226: 250 | P1226: 250 | Q1226: 51-100 | R1226: Sin descuento | S1226: 4 | T1226: 0
A1227: P0696 | B1227: Dairy, Bread & Batter | C1227: Alimentos y bebidas | D1227: Amul Lactose Free Milk | E1227: 25 | F1227: 4 | G1227: 24 | H1227: =ROUND(E1227-G1227,2) -> 1 | I1227: 0 | J1227: =TRUE() -> TRUE | K1227: =IF(J1227,1,0) -> 1 | L1227: Agotado | M1227: =ROUND(G1227*I1227,2) -> 0 | N1227: =ROUND(H1227*I1227,2) -> 0 | O1227: 250 | P1227: 250 | Q1227: 0-50 | R1227: 1-10% | S1227: 2 | T1227: 1
A1228: P0697 | B1228: Dairy, Bread & Batter | C1228: Alimentos y bebidas | D1228: The Bake Shop Whole Wheat Bread | E1228: 40 | F1228: 0 | G1228: 40 | H1228: =ROUND(E1228-G1228,2) -> 0 | I1228: 0 | J1228: =TRUE() -> TRUE | K1228: =IF(J1228,1,0) -> 1 | L1228: Agotado | M1228: =ROUND(G1228*I1228,2) -> 0 | N1228: =ROUND(H1228*I1228,2) -> 0 | O1228: 400 | P1228: 400 | Q1228: 0-50 | R1228: Sin descuento | S1228: 2 | T1228: 1
A1229: P0698 | B1229: Dairy, Bread & Batter | C1229: Alimentos y bebidas | D1229: Amul Slim Trim Skimmed Milk | E1229: 75 | F1229: 0 | G1229: 75 | H1229: =ROUND(E1229-G1229,2) -> 0 | I1229: 0 | J1229: =TRUE() -> TRUE | K1229: =IF(J1229,1,0) -> 1 | L1229: Agotado | M1229: =ROUND(G1229*I1229,2) -> 0 | N1229: =ROUND(H1229*I1229,2) -> 0 | O1229: 1000 | P1229: 1 | Q1229: 51-100 | R1229: Sin descuento | S1229: 2 | T1229: 1
A1230: P0699 | B1230: Dairy, Bread & Batter | C1230: Alimentos y bebidas | D1230: Amul Cheese Slices | E1230: 71 | F1230: 1 | G1230: 70 | H1230: =ROUND(E1230-G1230,2) -> 1 | I1230: 0 | J1230: =TRUE() -> TRUE | K1230: =IF(J1230,1,0) -> 1 | L1230: Agotado | M1230: =ROUND(G1230*I1230,2) -> 0 | N1230: =ROUND(H1230*I1230,2) -> 0 | O1230: 100 | P1230: 100 | Q1230: 51-100 | R1230: 1-10% | S1230: 2 | T1230: 1
A1231: P0700 | B1231: Dairy, Bread & Batter | C1231: Alimentos y bebidas | D1231: Amul Pizza Cheese - Mozzarella | E1231: 100 | F1231: 1 | G1231: 99 | H1231: =ROUND(E1231-G1231,2) -> 1 | I1231: 0 | J1231: =TRUE() -> TRUE | K1231: =IF(J1231,1,0) -> 1 | L1231: Agotado | M1231: =ROUND(G1231*I1231,2) -> 0 | N1231: =ROUND(H1231*I1231,2) -> 0 | O1231: 200 | P1231: 200 | Q1231: 51-100 | R1231: 1-10% | S1231: 2 | T1231: 1
A1232: P0701 | B1232: Dairy, Bread & Batter | C1232: Alimentos y bebidas | D1232: The Bake Shop Pizza Base Whole Wheat | E1232: 30 | F1232: 0 | G1232: 30 | H1232: =ROUND(E1232-G1232,2) -> 0 | I1232: 0 | J1232: =TRUE() -> TRUE | K1232: =IF(J1232,1,0) -> 1 | L1232: Agotado | M1232: =ROUND(G1232*I1232,2) -> 0 | N1232: =ROUND(H1232*I1232,2) -> 0 | O1232: 150 | P1232: 150 | Q1232: 0-50 | R1232: Sin descuento | S1232: 2 | T1232: 1
A1233: P0702 | B1233: Dairy, Bread & Batter | C1233: Alimentos y bebidas | D1233: Nestle A+ Slim Dahi - Low Fat | E1233: 78 | F1233: 3 | G1233: 75 | H1233: =ROUND(E1233-G1233,2) -> 3 | I1233: 0 | J1233: =TRUE() -> TRUE | K1233: =IF(J1233,1,0) -> 1 | L1233: Agotado | M1233: =ROUND(G1233*I1233,2) -> 0 | N1233: =ROUND(H1233*I1233,2) -> 0 | O1233: 400 | P1233: 400 | Q1233: 51-100 | R1233: 1-10% | S1233: 2 | T1233: 1
A1234: P0703 | B1234: Dairy, Bread & Batter | C1234: Alimentos y bebidas | D1234: Britannia Cheese Garlic Bread | E1234: 35 | F1234: 0 | G1234: 35 | H1234: =ROUND(E1234-G1234,2) -> 0 | I1234: 0 | J1234: =TRUE() -> TRUE | K1234: =IF(J1234,1,0) -> 1 | L1234: Agotado | M1234: =ROUND(G1234*I1234,2) -> 0 | N1234: =ROUND(H1234*I1234,2) -> 0 | O1234: 300 | P1234: 300 | Q1234: 0-50 | R1234: Sin descuento | S1234: 2 | T1234: 1
A1235: P0704 | B1235: Dairy, Bread & Batter | C1235: Alimentos y bebidas | D1235: The Bake Shop Whole Wheat Ladi Pav | E1235: 40 | F1235: 0 | G1235: 40 | H1235: =ROUND(E1235-G1235,2) -> 0 | I1235: 0 | J1235: =TRUE() -> TRUE | K1235: =IF(J1235,1,0) -> 1 | L1235: Agotado | M1235: =ROUND(G1235*I1235,2) -> 0 | N1235: =ROUND(H1235*I1235,2) -> 0 | O1235: 200 | P1235: 200 | Q1235: 0-50 | R1235: Sin descuento | S1235: 2 | T1235: 1
... A1251: P0720 | B1251: Dairy, Bread & Batter | C1251: Alimentos y bebidas | D1251: RRO Mozzarella Block Cheese | E1251: 295 | F1251: 50 | G1251: 147 | H1251: =ROUND(E1251-G1251,2) -> 148 | I1251: 0 | J1251: =TRUE() -> TRUE | K1251: =IF(J1251,1,0) -> 1 | L1251: Agotado | M1251: =ROUND(G1251*I1251,2) -> 0 | N1251: =ROUND(H1251*I1251,2) -> 0 | O1251: 200 | P1251: 200 | Q1251: 201-500 | R1251: 21% o mas | S1251: 2 | T1251: 1
...

Sheet productos_unicos
A1: id_producto | B1: categoria | C1: grupo | D1: producto | E1: precio_lista | F1: descuento_pct | G1: precio_venta | H1: ahorro_unitario | I1: cantidad_disponible | J1: agotado | K1: agotado_num | L1: nivel_stock | M1: valor_inventario | N1: ahorro_potencial | O1: peso_gramos | P1: cantidad_paquete | Q1: rango_precio | R1: rango_descuento | S1: n_categorias | T1: es_listado_principal
A2: P0001 | B2: Fruits & Vegetables | C2: Alimentos y bebidas | D2: Onion | E2: 25 | F2: 16 | G2: 21 | H2: =ROUND(E2-G2,2) -> 4 | I2: 3 | J2: =FALSE() -> FALSE | K2: =IF(J2,1,0) -> 0 | L2: Medio (3-5) | M2: =ROUND(G2*I2,2) -> 63 | N2: =ROUND(H2*I2,2) -> 12 | O2: 1000 | P2: 1 | Q2: 0-50 | R2: 11-20% | S2: 1 | T2: 1
A3: P0002 | B3: Fruits & Vegetables | C3: Alimentos y bebidas | D3: Tomato Hybrid | E3: 42 | F3: 16 | G3: 35 | H3: =ROUND(E3-G3,2) -> 7 | I3: 3 | J3: =FALSE() -> FALSE | K3: =IF(J3,1,0) -> 0 | L3: Medio (3-5) | M3: =ROUND(G3*I3,2) -> 105 | N3: =ROUND(H3*I3,2) -> 21 | O3: 1000 | P3: 1 | Q3: 0-50 | R3: 11-20% | S3: 1 | T3: 1
A4: P0003 | B4: Fruits & Vegetables | C4: Alimentos y bebidas | D4: Tender Coconut | E4: 51 | F4: 15 | G4: 43 | H4: =ROUND(E4-G4,2) -> 8 | I4: 3 | J4: =FALSE() -> FALSE | K4: =IF(J4,1,0) -> 0 | L4: Medio (3-5) | M4: =ROUND(G4*I4,2) -> 129 | N4: =ROUND(H4*I4,2) -> 24 | O4: 58 | P4: 1 | Q4: 51-100 | R4: 11-20% | S4: 1 | T4: 1
A5: P0004 | B5: Fruits & Vegetables | C5: Alimentos y bebidas | D5: Coriander Leaves | E5: 20 | F5: 15 | G5: 17 | H5: =ROUND(E5-G5,2) -> 3 | I5: 3 | J5: =FALSE() -> FALSE | K5: =IF(J5,1,0) -> 0 | L5: Medio (3-5) | M5: =ROUND(G5*I5,2) -> 51 | N5: =ROUND(H5*I5,2) -> 9 | O5: 100 | P5: 100 | Q5: 0-50 | R5: 11-20% | S5: 1 | T5: 1
A6: P0005 | B6: Fruits & Vegetables | C6: Alimentos y bebidas | D6: Ladies Finger | E6: 14 | F6: 14 | G6: 12 | H6: =ROUND(E6-G6,2) -> 2 | I6: 3 | J6: =FALSE() -> FALSE | K6: =IF(J6,1,0) -> 0 | L6: Medio (3-5) | M6: =ROUND(G6*I6,2) -> 36 | N6: =ROUND(H6*I6,2) -> 6 | O6: 250 | P6: 250 | Q6: 0-50 | R6: 11-20% | S6: 1 | T6: 1
A7: P0006 | B7: Fruits & Vegetables | C7: Alimentos y bebidas | D7: Potato | E7: 35 | F7: 17 | G7: 29 | H7: =ROUND(E7-G7,2) -> 6 | I7: 3 | J7: =FALSE() -> FALSE | K7: =IF(J7,1,0) -> 0 | L7: Medio (3-5) | M7: =ROUND(G7*I7,2) -> 87 | N7: =ROUND(H7*I7,2) -> 18 | O7: 1000 | P7: 1 | Q7: 0-50 | R7: 11-20% | S7: 1 | T7: 1
A8: P0007 | B8: Fruits & Vegetables | C8: Alimentos y bebidas | D8: Lemon | E8: 75 | F8: 16 | G8: 63 | H8: =ROUND(E8-G8,2) -> 12 | I8: 3 | J8: =FALSE() -> FALSE | K8: =IF(J8,1,0) -> 0 | L8: Medio (3-5) | M8: =ROUND(G8*I8,2) -> 189 | N8: =ROUND(H8*I8,2) -> 36 | O8: 200 | P8: 200 | Q8: 51-100 | R8: 11-20% | S8: 1 | T8: 1
A9: P0008 | B9: Fruits & Vegetables | C9: Alimentos y bebidas | D9: Watermelon | E9: 58 | F9: 15 | G9: 49 | H9: =ROUND(E9-G9,2) -> 9 | I9: 3 | J9: =FALSE() -> FALSE | K9: =IF(J9,1,0) -> 0 | L9: Medio (3-5) | M9: =ROUND(G9*I9,2) -> 147 | N9: =ROUND(H9*I9,2) -> 27 | O9: 58 | P9: 1 | Q9: 51-100 | R9: 11-20% | S9: 1 | T9: 1
A10: P0009 | B10: Fruits & Vegetables | C10: Alimentos y bebidas | D10: Capsicum Green | E10: 23 | F10: 17 | G10: 19 | H10: =ROUND(E10-G10,2) -> 4 | I10: 3 | J10: =FALSE() -> FALSE | K10: =IF(J10,1,0) -> 0 | L10: Medio (3-5) | M10: =ROUND(G10*I10,2) -> 57 | N10: =ROUND(H10*I10,2) -> 12 | O10: 250 | P10: 250 | Q10: 0-50 | R10: 11-20% | S10: 1 | T10: 1
A11: P0010 | B11: Fruits & Vegetables | C11: Alimentos y bebidas | D11: Chilli Green | E11: 19 | F11: 15 | G11: 16 | H11: =ROUND(E11-G11,2) -> 3 | I11: 3 | J11: =FALSE() -> FALSE | K11: =IF(J11,1,0) -> 0 | L11: Medio (3-5) | M11: =ROUND(G11*I11,2) -> 48 | N11: =ROUND(H11*I11,2) -> 9 | O11: 100 | P11: 100 | Q11: 0-50 | R11: 11-20% | S11: 1 | T11: 1
A12: P0011 | B12: Fruits & Vegetables | C12: Alimentos y bebidas | D12: Banana Robusta | E12: 29 | F12: 17 | G12: 24 | H12: =ROUND(E12-G12,2) -> 5 | I12: 3 | J12: =FALSE() -> FALSE | K12: =IF(J12,1,0) -> 0 | L12: Medio (3-5) | M12: =ROUND(G12*I12,2) -> 72 | N12: =ROUND(H12*I12,2) -> 15 | O12: 348 | P12: 6 | Q12: 0-50 | R12: 11-20% | S12: 1 | T12: 1
A13: P0012 | B13: Fruits & Vegetables | C13: Alimentos y bebidas | D13: Garlic Indian | E13: 11 | F13: 18 | G13: 9 | H13: =ROUND(E13-G13,2) -> 2 | I13: 3 | J13: =FALSE() -> FALSE | K13: =IF(J13,1,0) -> 0 | L13: Medio (3-5) | M13: =ROUND(G13*I13,2) -> 27 | N13: =ROUND(H13*I13,2) -> 6 | O13: 100 | P13: 100 | Q13: 0-50 | R13: 11-20% | S13: 1 | T13: 1
... A88: P0087 | B88: Fruits & Vegetables | C88: Alimentos y bebidas | D88: Garlic | E88: 17 | F88: 23 | G88: 13 | H88: =ROUND(E88-G88,2) -> 4 | I88: 3 | J88: =FALSE() -> FALSE | K88: =IF(J88,1,0) -> 0 | L88: Medio (3-5) | M88: =ROUND(G88*I88,2) -> 39 | N88: =ROUND(H88*I88,2) -> 12 | O88: 200 | P88: 200 | Q88: 0-50 | R88: 21% o mas | S88: 1 | T88: 1
A89: P0088 | B89: Fruits & Vegetables | C89: Alimentos y bebidas | D89: Carrot | E89: 13 | F89: 15 | G89: 11 | H89: =ROUND(E89-G89,2) -> 2 | I89: 0 | J89: =TRUE() -> TRUE | K89: =IF(J89,1,0) -> 1 | L89: Agotado | M89: =ROUND(G89*I89,2) -> 0 | N89: =ROUND(H89*I89,2) -> 0 | O89: 250 | P89: 200 | Q89: 0-50 | R89: 11-20% | S89: 1 | T89: 1
A90: P0089 | B90: Fruits & Vegetables | C90: Alimentos y bebidas | D90: Beetroot | E90: 11 | F90: 18 | G90: 9 | H90: =ROUND(E90-G90,2) -> 2 | I90: 0 | J90: =TRUE() -> TRUE | K90: =IF(J90,1,0) -> 1 | L90: Agotado | M90: =ROUND(G90*I90,2) -> 0 | N90: =ROUND(H90*I90,2) -> 0 | O90: 250 | P90: 250 | Q90: 0-50 | R90: 11-20% | S90: 1 | T90: 1
A91: P0090 | B91: Fruits & Vegetables | C91: Alimentos y bebidas | D91: Moong Sprouts | E91: 35 | F91: 17 | G91: 29 | H91: =ROUND(E91-G91,2) -> 6 | I91: 0 | J91: =TRUE() -> TRUE | K91: =IF(J91,1,0) -> 1 | L91: Agotado | M91: =ROUND(G91*I91,2) -> 0 | N91: =ROUND(H91*I91,2) -> 0 | O91: 200 | P91: 200 | Q91: 0-50 | R91: 11-20% | S91: 1 | T91: 1
A92: P0091 | B92: Fruits & Vegetables | C92: Alimentos y bebidas | D92: Safal Frozen Mixed Vegetables | E92: 60 | F92: 5 | G92: 57 | H92: =ROUND(E92-G92,2) -> 3 | I92: 0 | J92: =TRUE() -> TRUE | K92: =IF(J92,1,0) -> 1 | L92: Agotado | M92: =ROUND(G92*I92,2) -> 0 | N92: =ROUND(H92*I92,2) -> 0 | O92: 500 | P92: 500 | Q92: 51-100 | R92: 1-10% | S92: 4 | T92: 1
A93: P0092 | B93: Fruits & Vegetables | C93: Alimentos y bebidas | D93: Safal Frozen Corn | E93: 41 | F93: 4 | G93: 39 | H93: =ROUND(E93-G93,2) -> 2 | I93: 0 | J93: =TRUE() -> TRUE | K93: =IF(J93,1,0) -> 1 | L93: Agotado | M93: =ROUND(G93*I93,2) -> 0 | N93: =ROUND(H93*I93,2) -> 0 | O93: 200 | P93: 200 | Q93: 0-50 | R93: 1-10% | S93: 4 | T93: 1
A94: P0093 | B94: Fruits & Vegetables | C94: Alimentos y bebidas | D94: Safal Frozen - Sweet Corn | E94: 160 | F94: 5 | G94: 152 | H94: =ROUND(E94-G94,2) -> 8 | I94: 0 | J94: =TRUE() -> TRUE | K94: =IF(J94,1,0) -> 1 | L94: Agotado | M94: =ROUND(G94*I94,2) -> 0 | N94: =ROUND(H94*I94,2) -> 0 | O94: 1000 | P94: 1 | Q94: 101-200 | R94: 1-10% | S94: 4 | T94: 1
A95: P0094 | B95: Cooking Essentials | C95: Alimentos y bebidas | D95: Maggi 2 Minute Masala Noodles | E95: 12 | F95: 0 | G95: 12 | H95: =ROUND(E95-G95,2) -> 0 | I95: 6 | J95: =FALSE() -> FALSE | K95: =IF(J95,1,0) -> 0 | L95: Alto (6) | M95: =ROUND(G95*I95,2) -> 72 | N95: =ROUND(H95*I95,2) -> 0 | O95: 70 | P95: 70 | Q95: 0-50 | R95: Sin descuento | S95: 5 | T95: 1
A96: P0095 | B96: Cooking Essentials | C96: Alimentos y bebidas | D96: iD Idli & Dosa Batter | E96: 80 | F96: 15 | G96: 68 | H96: =ROUND(E96-G96,2) -> 12 | I96: 6 | J96: =FALSE() -> FALSE | K96: =IF(J96,1,0) -> 0 | L96: Alto (6) | M96: =ROUND(G96*I96,2) -> 408 | N96: =ROUND(H96*I96,2) -> 72 | O96: 1000 | P96: 1 | Q96: 51-100 | R96: 11-20% | S96: 7 | T96: 1
A97: P0096 | B97: Cooking Essentials | C97: Alimentos y bebidas | D97: Tata Salt | E97: 24 | F97: 0 | G97: 24 | H97: =ROUND(E97-G97,2) -> 0 | I97: 6 | J97: =FALSE() -> FALSE | K97: =IF(J97,1,0) -> 0 | L97: Alto (6) | M97: =ROUND(G97*I97,2) -> 144 | N97: =ROUND(H97*I97,2) -> 0 | O97: 1000 | P97: 1 | Q97: 0-50 | R97: Sin descuento | S97: 2 | T97: 1
A98: P0097 | B98: Cooking Essentials | C98: Alimentos y bebidas | D98: Arden Eggs White | E98: 97 | F98: 0 | G98: 97 | H98: =ROUND(E98-G98,2) -> 0 | I98: 4 | J98: =FALSE() -> FALSE | K98: =IF(J98,1,0) -> 0 | L98: Medio (3-5) | M98: =ROUND(G98*I98,2) -> 388 | N98: =ROUND(H98*I98,2) -> 0 | O98: 696 | P98: 12 | Q98: 51-100 | R98: Sin descuento | S98: 5 | T98: 1
A99: P0098 | B99: Cooking Essentials | C99: Alimentos y bebidas | D99: Arden Eggs White | E99: 65 | F99: 15 | G99: 55 | H99: =ROUND(E99-G99,2) -> 10 | I99: 4 | J99: =FALSE() -> FALSE | K99: =IF(J99,1,0) -> 0 | L99: Medio (3-5) | M99: =ROUND(G99*I99,2) -> 220 | N99: =ROUND(H99*I99,2) -> 40 | O99: 348 | P99: 6 | Q99: 51-100 | R99: 11-20% | S99: 5 | T99: 1
A100: P0099 | B100: Cooking Essentials | C100: Alimentos y bebidas | D100: Fortune Sunlite Refined Sunflower (Pouch) | E100: 230 | F100: 4 | G100: 219 | H100: =ROUND(E100-G100,2) -> 11 | I100: 6 | J100: =FALSE() -> FALSE | K100: =IF(J100,1,0) -> 0 | L100: Alto (6) | M100: =ROUND(G100*I100,2) -> 1314 | N100: =ROUND(H100*I100,2) -> 66 | O100: 1000 | P100: 1 | Q100: 201-500 | R100: 1-10% | S100: 2 | T100: 1
A101: P0100 | B101: Cooking Essentials | C101: Alimentos y bebidas | D101: Aashirvaad Superior MP Atta | E101: 250 | F101: 2 | G101: 245 | H101: =ROUND(E101-G101,2) -> 5 | I101: 6 | J101: =FALSE() -> FALSE | K101: =IF(J101,1,0) -> 0 | L101: Alto (6) | M101: =ROUND(G101*I101,2) -> 1470 | N101: =ROUND(H101*I101,2) -> 30 | O101: 5000 | P101: 5 | Q101: 201-500 | R101: 1-10% | S101: 2 | T101: 1
A102: P0101 | B102: Cooking Essentials | C102: Alimentos y bebidas | D102: Amul Pure Ghee (Pouch) | E102: 255 | F102: 2 | G102: 249 | H102: =ROUND(E102-G102,2) -> 6 | I102: 6 | J102: =FALSE() -> FALSE | K102: =IF(J102,1,0) -> 0 | L102: Alto (6) | M102: =ROUND(G102*I102,2) -> 1494 | N102: =ROUND(H102*I102,2) -> 36 | O102: 500 | P102: 500 | Q102: 201-500 | R102: 1-10% | S102: 2 | T102: 1
A103: P0102 | B103: Cooking Essentials | C103: Alimentos y bebidas | D103: Arden Eggs Brown | E103: 85 | F103: 7 | G103: 79 | H103: =ROUND(E103-G103,2) -> 6 | I103: 4 | J103: =FALSE() -> FALSE | K103: =IF(J103,1,0) -> 0 | L103: Medio (3-5) | M103: =ROUND(G103*I103,2) -> 316 | N103: =ROUND(H103*I103,2) -> 24 | O103: 348 | P103: 6 | Q103: 51-100 | R103: 1-10% | S103: 5 | T103: 1
A104: P0103 | B104: Cooking Essentials | C104: Alimentos y bebidas | D104: Tata Salt Lite | E104: 40 | F104: 10 | G104: 36 | H104: =ROUND(E104-G104,2) -> 4 | I104: 6 | J104: =FALSE() -> FALSE | K104: =IF(J104,1,0) -> 0 | L104: Alto (6) | M104: =ROUND(G104*I104,2) -> 216 | N104: =ROUND(H104*I104,2) -> 24 | O104: 1000 | P104: 1 | Q104: 0-50 | R104: 1-10% | S104: 2 | T104: 1
A105: P0104 | B105: Cooking Essentials | C105: Alimentos y bebidas | D105: Saffola Gold Oil (Pouch) | E105: 215 | F105: 0 | G105: 215 | H105: =ROUND(E105-G105,2) -> 0 | I105: 6 | J105: =FALSE() -> FALSE | K105: =IF(J105,1,0) -> 0 | L105: Alto (6) | M105: =ROUND(G105*I105,2) -> 1290 | N105: =ROUND(H105*I105,2) -> 0 | O105: 1000 | P105: 1 | Q105: 201-500 | R105: Sin descuento | S105: 2 | T105: 1
A106: P0105 | B106: Cooking Essentials | C106: Alimentos y bebidas | D106: Fortune Sunlite Refined Sunflower (Jar) | E106: 925 | F106: 0 | G106: 925 | H106: =ROUND(E106-G106,2) -> 0 | I106: 6 | J106: =FALSE() -> FALSE | K106: =IF(J106,1,0) -> 0 | L106: Alto (6) | M106: =ROUND(G106*I106,2) -> 5550 | N106: =ROUND(H106*I106,2) -> 0 | O106: 5000 | P106: 5 | Q106: 500+ | R106: Sin descuento | S106: 2 | T106: 1
... A544: P0543 | B544: Cooking Essentials | C544: Alimentos y bebidas | D544: Figaro Pure Olive Oil | E544: 325 | F544: 8 | G544: 299 | H544: =ROUND(E544-G544,2) -> 26 | I544: 1 | J544: =FALSE() -> FALSE | K544: =IF(J544,1,0) -> 0 | L544: Bajo (1-2) | M544: =ROUND(G544*I544,2) -> 299 | N544: =ROUND(H544*I544,2) -> 26 | O544: 200 | P544: 200 | Q544: 201-500 | R544: 1-10% | S544: 2 | T544: 1
A545: P0544 | B545: Cooking Essentials | C545: Alimentos y bebidas | D545: Madhur Sugar | E545: 60 | F545: 6 | G545: 56 | H545: =ROUND(E545-G545,2) -> 4 | I545: 0 | J545: =TRUE() -> TRUE | K545: =IF(J545,1,0) -> 1 | L545: Agotado | M545: =ROUND(G545*I545,2) -> 0 | N545: =ROUND(H545*I545,2) -> 0 | O545: 1000 | P545: 1 | Q545: 51-100 | R545: 1-10% | S545: 2 | T545: 1
A546: P0545 | B546: Cooking Essentials | C546: Alimentos y bebidas | D546: Amul Fresh Cream | E546: 63 | F546: 0 | G546: 63 | H546: =ROUND(E546-G546,2) -> 0 | I546: 0 | J546: =TRUE() -> TRUE | K546: =IF(J546,1,0) -> 1 | L546: Agotado | M546: =ROUND(G546*I546,2) -> 0 | N546: =ROUND(H546*I546,2) -> 0 | O546: 250 | P546: 250 | Q546: 51-100 | R546: Sin descuento | S546: 4 | T546: 1
A547: P0546 | B547: Cooking Essentials | C547: Alimentos y bebidas | D547: Madhur Pure And Hygienic Sugar | E547: 295 | F547: 9 | G547: 266 | H547: =ROUND(E547-G547,2) -> 29 | I547: 0 | J547: =TRUE() -> TRUE | K547: =IF(J547,1,0) -> 1 | L547: Agotado | M547: =ROUND(G547*I547,2) -> 0 | N547: =ROUND(H547*I547,2) -> 0 | O547: 5000 | P547: 5 | Q547: 201-500 | R547: 1-10% | S547: 2 | T547: 1
A548: P0547 | B548: Cooking Essentials | C548: Alimentos y bebidas | D548: Satyam Poha Jada | E548: 35 | F548: 8 | G548: 32 | H548: =ROUND(E548-G548,2) -> 3 | I548: 0 | J548: =TRUE() -> TRUE | K548: =IF(J548,1,0) -> 1 | L548: Agotado | M548: =ROUND(G548*I548,2) -> 0 | N548: =ROUND(H548*I548,2) -> 0 | O548: 500 | P548: 500 | Q548: 0-50 | R548: 1-10% | S548: 2 | T548: 1
A549: P0548 | B549: Cooking Essentials | C549: Alimentos y bebidas | D549: Aashirvaad Superior MP Whole Wheat Atta | E549: 53 | F549: 1 | G549: 52 | H549: =ROUND(E549-G549,2) -> 1 | I549: 0 | J549: =TRUE() -> TRUE | K549: =IF(J549,1,0) -> 1 | L549: Agotado | M549: =ROUND(G549*I549,2) -> 0 | N549: =ROUND(H549*I549,2) -> 0 | O549: 1000 | P549: 1 | Q549: 51-100 | R549: 1-10% | S549: 2 | T549: 1
A550: P0549 | B550: Cooking Essentials | C550: Alimentos y bebidas | D550: Fortune Soyabean Oil | E550: 210 | F550: 13 | G550: 181 | H550: =ROUND(E550-G550,2) -> 29 | I550: 0 | J550: =TRUE() -> TRUE | K550: =IF(J550,1,0) -> 1 | L550: Agotado | M550: =ROUND(G550*I550,2) -> 0 | N550: =ROUND(H550*I550,2) -> 0 | O550: 1000 | P550: 1 | Q550: 201-500 | R550: 11-20% | S550: 2 | T550: 1
A551: P0550 | B551: Cooking Essentials | C551: Alimentos y bebidas | D551: Maggi Masala Ae Magic | E551: 58 | F551: 6 | G551: 54 | H551: =ROUND(E551-G551,2) -> 4 | I551: 0 | J551: =TRUE() -> TRUE | K551: =IF(J551,1,0) -> 1 | L551: Agotado | M551: =ROUND(G551*I551,2) -> 0 | N551: =ROUND(H551*I551,2) -> 0 | O551: 72 | P551: 72 | Q551: 51-100 | R551: 1-10% | S551: 2 | T551: 1
A552: P0551 | B552: Cooking Essentials | C552: Alimentos y bebidas | D552: Aashirvaad Iodised Salt | E552: 22 | F552: 13 | G552: 19 | H552: =ROUND(E552-G552,2) -> 3 | I552: 0 | J552: =TRUE() -> TRUE | K552: =IF(J552,1,0) -> 1 | L552: Agotado | M552: =ROUND(G552*I552,2) -> 0 | N552: =ROUND(H552*I552,2) -> 0 | O552: 1000 | P552: 1 | Q552: 0-50 | R552: 11-20% | S552: 2 | T552: 1
A553: P0552 | B553: Cooking Essentials | C553: Alimentos y bebidas | D553: Maggi 2-Minute Instant Noodles - Masala | E553: 44 | F553: 0 | G553: 44 | H553: =ROUND(E553-G553,2) -> 0 | I553: 0 | J553: =TRUE() -> TRUE | K553: =IF(J553,1,0) -> 1 | L553: Agotado | M553: =ROUND(G553*I553,2) -> 0 | N553: =ROUND(H553*I553,2) -> 0 | O553: 280 | P553: 280 | Q553: 0-50 | R553: Sin descuento | S553: 5 | T553: 1
A554: P0553 | B554: Cooking Essentials | C554: Alimentos y bebidas | D554: Popular Essentials Phool Makhana (Jumbo Size) | E554: 150 | F554: 14 | G554: 128 | H554: =ROUND(E554-G554,2) -> 22 | I554: 0 | J554: =TRUE() -> TRUE | K554: =IF(J554,1,0) -> 1 | L554: Agotado | M554: =ROUND(G554*I554,2) -> 0 | N554: =ROUND(H554*I554,2) -> 0 | O554: 100 | P554: 100 | Q554: 101-200 | R554: 11-20% | S554: 2 | T554: 1
A555: P0554 | B555: Cooking Essentials | C555: Alimentos y bebidas | D555: Aashirvaad Atta With Mutigrains | E555: 315 | F555: 8 | G555: 287 | H555: =ROUND(E555-G555,2) -> 28 | I555: 0 | J555: =TRUE() -> TRUE | K555: =IF(J555,1,0) -> 1 | L555: Agotado | M555: =ROUND(G555*I555,2) -> 0 | N555: =ROUND(H555*I555,2) -> 0 | O555: 5000 | P555: 5 | Q555: 201-500 | R555: 1-10% | S555: 2 | T555: 1
A556: P0555 | B556: Cooking Essentials | C556: Alimentos y bebidas | D556: Tata Sampann Poha | E556: 44 | F556: 6 | G556: 41 | H556: =ROUND(E556-G556,2) -> 3 | I556: 0 | J556: =TRUE() -> TRUE | K556: =IF(J556,1,0) -> 1 | L556: Agotado | M556: =ROUND(G556*I556,2) -> 0 | N556: =ROUND(H556*I556,2) -> 0 | O556: 500 | P556: 500 | Q556: 0-50 | R556: 1-10% | S556: 2 | T556: 1
... A607: P0606 | B607: Cooking Essentials | C607: Alimentos y bebidas | D607: Godrej Yummiez Chicken Breakfast Salami | E607: 150 | F607: 4 | G607: 143 | H607: =ROUND(E607-G607,2) -> 7 | I607: 0 | J607: =TRUE() -> TRUE | K607: =IF(J607,1,0) -> 1 | L607: Agotado | M607: =ROUND(G607*I607,2) -> 0 | N607: =ROUND(H607*I607,2) -> 0 | O607: 250 | P607: 250 | Q607: 101-200 | R607: 1-10% | S607: 6 | T607: 1
A608: P0607 | B608: Cooking Essentials | C608: Alimentos y bebidas | D608: Everest Saffron Kesar | E608: 120 | F608: 0 | G608: 120 | H608: =ROUND(E608-G608,2) -> 0 | I608: 0 | J608: =TRUE() -> TRUE | K608: =IF(J608,1,0) -> 1 | L608: Agotado | M608: =ROUND(G608*I608,2) -> 0 | N608: =ROUND(H608*I608,2) -> 0 | O608: 1 | Q608: 101-200 | R608: Sin descuento | S608: 2 | T608: 1
A609: P0608 | B609: Dairy, Bread & Batter | C609: Alimentos y bebidas | D609: Mother Dairy Toned Milk Pouch | E609: 25 | F609: 0 | G609: 25 | H609: =ROUND(E609-G609,2) -> 0 | I609: 4 | J609: =FALSE() -> FALSE | K609: =IF(J609,1,0) -> 0 | L609: Medio (3-5) | M609: =ROUND(G609*I609,2) -> 100 | N609: =ROUND(H609*I609,2) -> 0 | O609: 500 | P609: 500 | Q609: 0-50 | R609: Sin descuento | S609: 2 | T609: 1
A610: P0609 | B610: Dairy, Bread & Batter | C610: Alimentos y bebidas | D610: Mother Dairy Classic Curd | E610: 30 | F610: 3 | G610: 29 | H610: =ROUND(E610-G610,2) -> 1 | I610: 6 | J610: =FALSE() -> FALSE | K610: =IF(J610,1,0) -> 0 | L610: Alto (6) | M610: =ROUND(G610*I610,2) -> 174 | N610: =ROUND(H610*I610,2) -> 6 | O610: 400 | P610: 400 | Q610: 0-50 | R610: 1-10% | S610: 2 | T610: 1
A611: P0610 | B611: Dairy, Bread & Batter | C611: Alimentos y bebidas | D611: Mother Dairy Ultra Full Cream Milk | E611: 31 | F611: 0 | G611: 31 | H611: =ROUND(E611-G611,2) -> 0 | I611: 4 | J611: =FALSE() -> FALSE | K611: =IF(J611,1,0) -> 0 | L611: Medio (3-5) | M611: =ROUND(G611*I611,2) -> 124 | N611: =ROUND(H611*I611,2) -> 0 | O611: 500 | P611: 500 | Q611: 0-50 | R611: Sin descuento | S611: 2 | T611: 1
A612: P0611 | B612: Dairy, Bread & Batter | C612: Alimentos y bebidas | D612: Amul Butter - Pasteurised | E612: 50 | F612: 2 | G612: 49 | H612: =ROUND(E612-G612,2) -> 1 | I612: 6 | J612: =FALSE() -> FALSE | K612: =IF(J612,1,0) -> 0 | L612: Alto (6) | M612: =ROUND(G612*I612,2) -> 294 | N612: =ROUND(H612*I612,2) -> 6 | O612: 100 | P612: 100 | Q612: 0-50 | R612: 1-10% | S612: 2 | T612: 1
A613: P0612 | B613: Dairy, Bread & Batter | C613: Alimentos y bebidas | D613: Britannia Sandwich White Bread | E613: 33 | F613: 0 | G613: 33 | H613: =ROUND(E613-G613,2) -> 0 | I613: 4 | J613: =FALSE() -> FALSE | K613: =IF(J613,1,0) -> 0 | L613: Medio (3-5) | M613: =ROUND(G613*I613,2) -> 132 | N613: =ROUND(H613*I613,2) -> 0 | O613: 350 | P613: 350 | Q613: 0-50 | R613: Sin descuento | S613: 2 | T613: 1
A614: P0613 | B614: Dairy, Bread & Batter | C614: Alimentos y bebidas | D614: iD Curd Pouch | E614: 35 | F614: 2 | G614: 34 | H614: =ROUND(E614-G614,2) -> 1 | I614: 6 | J614: =FALSE() -> FALSE | K614: =IF(J614,1,0) -> 0 | L614: Alto (6) | M614: =ROUND(G614*I614,2) -> 204 | N614: =ROUND(H614*I614,2) -> 6 | O614: 400 | P614: 400 | Q614: 0-50 | R614: 1-10% | S614: 2 | T614: 1
A615: P0614 | B615: Dairy, Bread & Batter | C615: Alimentos y bebidas | D615: Britannia 100% Whole Wheat Bread | E615: 45 | F615: 0 | G615: 45 | H615: =ROUND(E615-G615,2) -> 0 | I615: 4 | J615: =FALSE() -> FALSE | K615: =IF(J615,1,0) -> 0 | L615: Medio (3-5) | M615: =ROUND(G615*I615,2) -> 180 | N615: =ROUND(H615*I615,2) -> 0 | O615: 450 | P615: 450 | Q615: 0-50 | R615: Sin descuento | S615: 2 | T615: 1
A616: P0615 | B616: Dairy, Bread & Batter | C616: Alimentos y bebidas | D616: Britannia Healthy Slice Sandwich Bread | E616: 40 | F616: 0 | G616: 40 | H616: =ROUND(E616-G616,2) -> 0 | I616: 4 | J616: =FALSE() -> FALSE | K616: =IF(J616,1,0) -> 0 | L616: Medio (3-5) | M616: =ROUND(G616*I616,2) -> 160 | N616: =ROUND(H616*I616,2) -> 0 | O616: 450 | P616: 450 | Q616: 0-50 | R616: Sin descuento | S616: 2 | T616: 1
A617: P0616 | B617: Dairy, Bread & Batter | C617: Alimentos y bebidas | D617: Gowardhan Classic Block Fresh Paneer | E617: 89 | F617: 8 | G617: 81 | H617: =ROUND(E617-G617,2) -> 8 | I617: 6 | J617: =FALSE() -> FALSE | K617: =IF(J617,1,0) -> 0 | L617: Alto (6) | M617: =ROUND(G617*I617,2) -> 486 | N617: =ROUND(H617*I617,2) -> 48 | O617: 200 | P617: 200 | Q617: 51-100 | R617: 1-10% | S617: 2 | T617: 1
A618: P0617 | B618: Dairy, Bread & Batter | C618: Alimentos y bebidas | D618: Amul Processed Cheese Cubes | E618: 106 | F618: 4 | G618: 101 | H618: =ROUND(E618-G618,2) -> 5 | I618: 6 | J618: =FALSE() -> FALSE | K618: =IF(J618,1,0) -> 0 | L618: Alto (6) | M618: =ROUND(G618*I618,2) -> 606 | N618: =ROUND(H618*I618,2) -> 30 | O618: 200 | P618: 200 | Q618: 101-200 | R618: 1-10% | S618: 2 | T618: 1
A619: P0618 | B619: Dairy, Bread & Batter | C619: Alimentos y bebidas | D619: Britannia Pav | E619: 22 | F619: 0 | G619: 22 | H619: =ROUND(E619-G619,2) -> 0 | I619: 4 | J619: =FALSE() -> FALSE | K619: =IF(J619,1,0) -> 0 | L619: Medio (3-5) | M619: =ROUND(G619*I619,2) -> 88 | N619: =ROUND(H619*I619,2) -> 0 | O619: 250 | P619: 250 | Q619: 0-50 | R619: Sin descuento | S619: 2 | T619: 1
A620: P0619 | B620: Dairy, Bread & Batter | C620: Alimentos y bebidas | D620: Amul Butter - Pasteurised | E620: 245 | F620: 2 | G620: 240 | H620: =ROUND(E620-G620,2) -> 5 | I620: 6 | J620: =FALSE() -> FALSE | K620: =IF(J620,1,0) -> 0 | L620: Alto (6) | M620: =ROUND(G620*I620,2) -> 1440 | N620: =ROUND(H620*I620,2) -> 30 | O620: 500 | P620: 500 | Q620: 201-500 | R620: 1-10% | S620: 2 | T620: 1
... A694: P0693 | B694: Dairy, Bread & Batter | C694: Alimentos y bebidas | D694: The Laughing Cow Cheese Spread Plain | E694: 110 | F694: 0 | G694: 110 | H694: =ROUND(E694-G694,2) -> 0 | I694: 6 | J694: =FALSE() -> FALSE | K694: =IF(J694,1,0) -> 0 | L694: Alto (6) | M694: =ROUND(G694*I694,2) -> 660 | N694: =ROUND(H694*I694,2) -> 0 | O694: 180 | P694: 180 | Q694: 101-200 | R694: Sin descuento | S694: 5 | T694: 1
A695: P0694 | B695: Dairy, Bread & Batter | C695: Alimentos y bebidas | D695: Amul Malai Paneer Fresh | E695: 76 | F695: 3 | G695: 73 | H695: =ROUND(E695-G695,2) -> 3 | I695: 0 | J695: =TRUE() -> TRUE | K695: =IF(J695,1,0) -> 1 | L695: Agotado | M695: =ROUND(G695*I695,2) -> 0 | N695: =ROUND(H695*I695,2) -> 0 | O695: 200 | P695: 200 | Q695: 51-100 | R695: 1-10% | S695: 2 | T695: 1
A696: P0695 | B696: Dairy, Bread & Batter | C696: Alimentos y bebidas | D696: Amul Taaza Toned Homogenised Milk | E696: 66 | F696: 3 | G696: 64 | H696: =ROUND(E696-G696,2) -> 2 | I696: 0 | J696: =TRUE() -> TRUE | K696: =IF(J696,1,0) -> 1 | L696: Agotado | M696: =ROUND(G696*I696,2) -> 0 | N696: =ROUND(H696*I696,2) -> 0 | O696: 1000 | P696: 1 | Q696: 51-100 | R696: 1-10% | S696: 2 | T696: 1
A697: P0696 | B697: Dairy, Bread & Batter | C697: Alimentos y bebidas | D697: Amul Lactose Free Milk | E697: 25 | F697: 4 | G697: 24 | H697: =ROUND(E697-G697,2) -> 1 | I697: 0 | J697: =TRUE() -> TRUE | K697: =IF(J697,1,0) -> 1 | L697: Agotado | M697: =ROUND(G697*I697,2) -> 0 | N697: =ROUND(H697*I697,2) -> 0 | O697: 250 | P697: 250 | Q697: 0-50 | R697: 1-10% | S697: 2 | T697: 1
A698: P0697 | B698: Dairy, Bread & Batter | C698: Alimentos y bebidas | D698: The Bake Shop Whole Wheat Bread | E698: 40 | F698: 0 | G698: 40 | H698: =ROUND(E698-G698,2) -> 0 | I698: 0 | J698: =TRUE() -> TRUE | K698: =IF(J698,1,0) -> 1 | L698: Agotado | M698: =ROUND(G698*I698,2) -> 0 | N698: =ROUND(H698*I698,2) -> 0 | O698: 400 | P698: 400 | Q698: 0-50 | R698: Sin descuento | S698: 2 | T698: 1
A699: P0698 | B699: Dairy, Bread & Batter | C699: Alimentos y bebidas | D699: Amul Slim Trim Skimmed Milk | E699: 75 | F699: 0 | G699: 75 | H699: =ROUND(E699-G699,2) -> 0 | I699: 0 | J699: =TRUE() -> TRUE | K699: =IF(J699,1,0) -> 1 | L699: Agotado | M699: =ROUND(G699*I699,2) -> 0 | N699: =ROUND(H699*I699,2) -> 0 | O699: 1000 | P699: 1 | Q699: 51-100 | R699: Sin descuento | S699: 2 | T699: 1
A700: P0699 | B700: Dairy, Bread & Batter | C700: Alimentos y bebidas | D700: Amul Cheese Slices | E700: 71 | F700: 1 | G700: 70 | H700: =ROUND(E700-G700,2) -> 1 | I700: 0 | J700: =TRUE() -> TRUE | K700: =IF(J700,1,0) -> 1 | L700: Agotado | M700: =ROUND(G700*I700,2) -> 0 | N700: =ROUND(H700*I700,2) -> 0 | O700: 100 | P700: 100 | Q700: 51-100 | R700: 1-10% | S700: 2 | T700: 1
A701: P0700 | B701: Dairy, Bread & Batter | C701: Alimentos y bebidas | D701: Amul Pizza Cheese - Mozzarella | E701: 100 | F701: 1 | G701: 99 | H701: =ROUND(E701-G701,2) -> 1 | I701: 0 | J701: =TRUE() -> TRUE | K701: =IF(J701,1,0) -> 1 | L701: Agotado | M701: =ROUND(G701*I701,2) -> 0 | N701: =ROUND(H701*I701,2) -> 0 | O701: 200 | P701: 200 | Q701: 51-100 | R701: 1-10% | S701: 2 | T701: 1
A702: P0701 | B702: Dairy, Bread & Batter | C702: Alimentos y bebidas | D702: The Bake Shop Pizza Base Whole Wheat | E702: 30 | F702: 0 | G702: 30 | H702: =ROUND(E702-G702,2) -> 0 | I702: 0 | J702: =TRUE() -> TRUE | K702: =IF(J702,1,0) -> 1 | L702: Agotado | M702: =ROUND(G702*I702,2) -> 0 | N702: =ROUND(H702*I702,2) -> 0 | O702: 150 | P702: 150 | Q702: 0-50 | R702: Sin descuento | S702: 2 | T702: 1
A703: P0702 | B703: Dairy, Bread & Batter | C703: Alimentos y bebidas | D703: Nestle A+ Slim Dahi - Low Fat | E703: 78 | F703: 3 | G703: 75 | H703: =ROUND(E703-G703,2) -> 3 | I703: 0 | J703: =TRUE() -> TRUE | K703: =IF(J703,1,0) -> 1 | L703: Agotado | M703: =ROUND(G703*I703,2) -> 0 | N703: =ROUND(H703*I703,2) -> 0 | O703: 400 | P703: 400 | Q703: 51-100 | R703: 1-10% | S703: 2 | T703: 1
A704: P0703 | B704: Dairy, Bread & Batter | C704: Alimentos y bebidas | D704: Britannia Cheese Garlic Bread | E704: 35 | F704: 0 | G704: 35 | H704: =ROUND(E704-G704,2) -> 0 | I704: 0 | J704: =TRUE() -> TRUE | K704: =IF(J704,1,0) -> 1 | L704: Agotado | M704: =ROUND(G704*I704,2) -> 0 | N704: =ROUND(H704*I704,2) -> 0 | O704: 300 | P704: 300 | Q704: 0-50 | R704: Sin descuento | S704: 2 | T704: 1
A705: P0704 | B705: Dairy, Bread & Batter | C705: Alimentos y bebidas | D705: The Bake Shop Whole Wheat Ladi Pav | E705: 40 | F705: 0 | G705: 40 | H705: =ROUND(E705-G705,2) -> 0 | I705: 0 | J705: =TRUE() -> TRUE | K705: =IF(J705,1,0) -> 1 | L705: Agotado | M705: =ROUND(G705*I705,2) -> 0 | N705: =ROUND(H705*I705,2) -> 0 | O705: 200 | P705: 200 | Q705: 0-50 | R705: Sin descuento | S705: 2 | T705: 1
A706: P0705 | B706: Dairy, Bread & Batter | C706: Alimentos y bebidas | D706: Amul Cheese Spread Yummy Plain | E706: 85 | F706: 0 | G706: 85 | H706: =ROUND(E706-G706,2) -> 0 | I706: 0 | J706: =TRUE() -> TRUE | K706: =IF(J706,1,0) -> 1 | L706: Agotado | M706: =ROUND(G706*I706,2) -> 0 | N706: =ROUND(H706*I706,2) -> 0 | O706: 200 | P706: 200 | Q706: 51-100 | R706: Sin descuento | S706: 5 | T706: 1
... A721: P0720 | B721: Dairy, Bread & Batter | C721: Alimentos y bebidas | D721: RRO Mozzarella Block Cheese | E721: 295 | F721: 50 | G721: 147 | H721: =ROUND(E721-G721,2) -> 148 | I721: 0 | J721: =TRUE() -> TRUE | K721: =IF(J721,1,0) -> 1 | L721: Agotado | M721: =ROUND(G721*I721,2) -> 0 | N721: =ROUND(H721*I721,2) -> 0 | O721: 200 | P721: 200 | Q721: 201-500 | R721: 21% o mas | S721: 2 | T721: 1
A722: P0721 | B722: Packaged Food | C722: Alimentos y bebidas | D722: iD Malabar Parota | E722: 80 | F722: 10 | G722: 72 | H722: =ROUND(E722-G722,2) -> 8 | I722: 4 | J722: =FALSE() -> FALSE | K722: =IF(J722,1,0) -> 0 | L722: Medio (3-5) | M722: =ROUND(G722*I722,2) -> 288 | N722: =ROUND(H722*I722,2) -> 32 | O722: 400 | P722: 400 | Q722: 51-100 | R722: 1-10% | S722: 3 | T722: 1
A723: P0722 | B723: Packaged Food | C723: Alimentos y bebidas | D723: iD Wheat Lachha Paratha | E723: 80 | F723: 12 | G723: 70 | H723: =ROUND(E723-G723,2) -> 10 | I723: 6 | J723: =FALSE() -> FALSE | K723: =IF(J723,1,0) -> 0 | L723: Alto (6) | M723: =ROUND(G723*I723,2) -> 420 | N723: =ROUND(H723*I723,2) -> 60 | O723: 400 | P723: 400 | Q723: 51-100 | R723: 11-20% | S723: 3 | T723: 1
A724: P0723 | B724: Packaged Food | C724: Alimentos y bebidas | D724: McCain Aloo Tikki | E724: 110 | F724: 4 | G724: 105 | H724: =ROUND(E724-G724,2) -> 5 | I724: 6 | J724: =FALSE() -> FALSE | K724: =IF(J724,1,0) -> 0 | L724: Alto (6) | M724: =ROUND(G724*I724,2) -> 630 | N724: =ROUND(H724*I724,2) -> 30 | O724: 400 | P724: 400 | Q724: 101-200 | R724: 1-10% | S724: 3 | T724: 1
A725: P0724 | B725: Packaged Food | C725: Alimentos y bebidas | D725: McCain Smiles Cripsy Happy Potatoes | E725: 120 | F725: 5 | G725: 114 | H725: =ROUND(E725-G725,2) -> 6 | I725: 6 | J725: =FALSE() -> FALSE | K725: =IF(J725,1,0) -> 0 | L725: Alto (6) | M725: =ROUND(G725*I725,2) -> 684 | N725: =ROUND(H725*I725,2) -> 36 | O725: 415 | P725: 415 | Q725: 101-200 | R725: 1-10% | S725: 3 | T725: 1
A726: P0725 | B726: Packaged Food | C726: Alimentos y bebidas | D726: McCain Veggie Burger Patty | E726: 115 | F726: 3 | G726: 111 | H726: =ROUND(E726-G726,2) -> 4 | I726: 6 | J726: =FALSE() -> FALSE | K726: =IF(J726,1,0) -> 0 | L726: Alto (6) | M726: =ROUND(G726*I726,2) -> 666 | N726: =ROUND(H726*I726,2) -> 24 | O726: 360 | P726: 360 | Q726: 101-200 | R726: 1-10% | S726: 3 | T726: 1
A727: P0726 | B727: Packaged Food | C727: Alimentos y bebidas | D727: McCain Veggie Fingers | E727: 117 | F727: 5 | G727: 111 | H727: =ROUND(E727-G727,2) -> 6 | I727: 6 | J727: =FALSE() -> FALSE | K727: =IF(J727,1,0) -> 0 | L727: Alto (6) | M727: =ROUND(G727*I727,2) -> 666 | N727: =ROUND(H727*I727,2) -> 36 | O727: 400 | P727: 400 | Q727: 101-200 | R727: 1-10% | S727: 3 | T727: 1
A728: P0727 | B728: Packaged Food | C728: Alimentos y bebidas | D728: Whiskas Wet Meal (Adult - Cat Food) Chicken in Gravy | E728: 35 | F728: 2 | G728: 34 | H728: =ROUND(E728-G728,2) -> 1 | I728: 2 | J728: =FALSE() -> FALSE | K728: =IF(J728,1,0) -> 0 | L728: Bajo (1-2) | M728: =ROUND(G728*I728,2) -> 68 | N728: =ROUND(H728*I728,2) -> 2 | O728: 85 | P728: 85 | Q728: 0-50 | R728: 1-10% | S728: 3 | T728: 1
A729: P0728 | B729: Packaged Food | C729: Alimentos y bebidas | D729: McCain Chilli Garlic Potato Bites Crunchy Potato Nuggets | E729: 125 | F729: 5 | G729: 118 | H729: =ROUND(E729-G729,2) -> 7 | I729: 1 | J729: =FALSE() -> FALSE | K729: =IF(J729,1,0) -> 0 | L729: Bajo (1-2) | M729: =ROUND(G729*I729,2) -> 118 | N729: =ROUND(H729*I729,2) -> 7 | O729: 420 | P729: 420 | Q729: 101-200 | R729: 1-10% | S729: 3 | T729: 1
A730: P0729 | B730: Packaged Food | C730: Alimentos y bebidas | D730: Veeba Eggless Mayonnaise | E730: 79 | F730: 11 | G730: 70 | H730: =ROUND(E730-G730,2) -> 9 | I730: 5 | J730: =FALSE() -> FALSE | K730: =IF(J730,1,0) -> 0 | L730: Medio (3-5) | M730: =ROUND(G730*I730,2) -> 350 | N730: =ROUND(H730*I730,2) -> 45 | O730: 250 | P730: 250 | Q730: 51-100 | R730: 11-20% | S730: 3 | T730: 1
A731: P0730 | B731: Packaged Food | C731: Alimentos y bebidas | D731: Veeba Pasta And Pizza Sauce | E731: 75 | F731: 13 | G731: 65 | H731: =ROUND(E731-G731,2) -> 10 | I731: 5 | J731: =FALSE() -> FALSE | K731: =IF(J731,1,0) -> 0 | L731: Medio (3-5) | M731: =ROUND(G731*I731,2) -> 325 | N731: =ROUND(H731*I731,2) -> 50 | O731: 280 | P731: 280 | Q731: 51-100 | R731: 11-20% | S731: 3 | T731: 1
A732: P0731 | B732: Packaged Food | C732: Alimentos y bebidas | D732: Unibic Almond & Oats Protein Bar | E732: 40 | F732: 17 | G732: 33 | H732: =ROUND(E732-G732,2) -> 7 | I732: 4 | J732: =FALSE() -> FALSE | K732: =IF(J732,1,0) -> 0 | L732: Medio (3-5) | M732: =ROUND(G732*I732,2) -> 132 | N732: =ROUND(H732*I732,2) -> 28 | O732: 30 | P732: 30 | Q732: 0-50 | R732: 11-20% | S732: 3 | T732: 1
A733: P0732 | B733: Packaged Food | C733: Alimentos y bebidas | D733: McCain French Fries | E733: 120 | F733: 5 | G733: 114 | H733: =ROUND(E733-G733,2) -> 6 | I733: 1 | J733: =FALSE() -> FALSE | K733: =IF(J733,1,0) -> 0 | L733: Bajo (1-2) | M733: =ROUND(G733*I733,2) -> 114 | N733: =ROUND(H733*I733,2) -> 6 | O733: 420 | P733: 420 | Q733: 101-200 | R733: 1-10% | S733: 3 | T733: 1
... A997: P0996 | B997: Packaged Food | C997: Alimentos y bebidas | D997: MTR Roasted Vermicelli | E997: 105 | F997: 0 | G997: 105 | H997: =ROUND(E997-G997,2) -> 0 | I997: 4 | J997: =FALSE() -> FALSE | K997: =IF(J997,1,0) -> 0 | L997: Medio (3-5) | M997: =ROUND(G997*I997,2) -> 420 | N997: =ROUND(H997*I997,2) -> 0 | O997: 850 | P997: 850 | Q997: 101-200 | R997: Sin descuento | S997: 3 | T997: 1
A998: P0997 | B998: Packaged Food | C998: Alimentos y bebidas | D998: Kurkure Green Chutney, Rajasthani Style | E998: 20 | F998: 0 | G998: 20 | H998: =ROUND(E998-G998,2) -> 0 | I998: 0 | J998: =TRUE() -> TRUE | K998: =IF(J998,1,0) -> 1 | L998: Agotado | M998: =ROUND(G998*I998,2) -> 0 | N998: =ROUND(H998*I998,2) -> 0 | O998: 90 | P998: 90 | Q998: 0-50 | R998: Sin descuento | S998: 3 | T998: 1
A999: P0998 | B999: Packaged Food | C999: Alimentos y bebidas | D999: Kellogg's Chocos Combo Pack | E999: 60 | F999: 6 | G999: 56 | H999: =ROUND(E999-G999,2) -> 4 | I999: 0 | J999: =TRUE() -> TRUE | K999: =IF(J999,1,0) -> 1 | L999: Agotado | M999: =ROUND(G999*I999,2) -> 0 | N999: =ROUND(H999*I999,2) -> 0 | O999: 156 | P999: 156 | Q999: 51-100 | R999: 1-10% | S999: 3 | T999: 1
A1000: P0999 | B1000: Packaged Food | C1000: Alimentos y bebidas | D1000: Kissan Mixed Fruit Jam | E1000: 155 | F1000: 0 | G1000: 155 | H1000: =ROUND(E1000-G1000,2) -> 0 | I1000: 0 | J1000: =TRUE() -> TRUE | K1000: =IF(J1000,1,0) -> 1 | L1000: Agotado | M1000: =ROUND(G1000*I1000,2) -> 0 | N1000: =ROUND(H1000*I1000,2) -> 0 | O1000: 500 | P1000: 500 | Q1000: 101-200 | R1000: Sin descuento | S1000: 3 | T1000: 1
A1001: P1000 | B1001: Packaged Food | C1001: Alimentos y bebidas | D1001: Lijjat Urad Papad | E1001: 60 | F1001: 5 | G1001: 57 | H1001: =ROUND(E1001-G1001,2) -> 3 | I1001: 0 | J1001: =TRUE() -> TRUE | K1001: =IF(J1001,1,0) -> 1 | L1001: Agotado | M1001: =ROUND(G1001*I1001,2) -> 0 | N1001: =ROUND(H1001*I1001,2) -> 0 | O1001: 200 | P1001: 200 | Q1001: 51-100 | R1001: 1-10% | S1001: 3 | T1001: 1
A1002: P1001 | B1002: Packaged Food | C1002: Alimentos y bebidas | D1002: Mother's Recipe Ginger And Garlic Paste | E1002: 50 | F1002: 24 | G1002: 38 | H1002: =ROUND(E1002-G1002,2) -> 12 | I1002: 0 | J1002: =TRUE() -> TRUE | K1002: =IF(J1002,1,0) -> 1 | L1002: Agotado | M1002: =ROUND(G1002*I1002,2) -> 0 | N1002: =ROUND(H1002*I1002,2) -> 0 | O1002: 200 | P1002: 200 | Q1002: 0-50 | R1002: 21% o mas | S1002: 3 | T1002: 1
A1003: P1002 | B1003: Packaged Food | C1003: Alimentos y bebidas | D1003: Maggi Magic Cubes Chicken | E1003: 40 | F1003: 2 | G1003: 39 | H1003: =ROUND(E1003-G1003,2) -> 1 | I1003: 0 | J1003: =TRUE() -> TRUE | K1003: =IF(J1003,1,0) -> 1 | L1003: Agotado | M1003: =ROUND(G1003*I1003,2) -> 0 | N1003: =ROUND(H1003*I1003,2) -> 0 | O1003: 40 | P1003: 40 | Q1003: 0-50 | R1003: 1-10% | S1003: 3 | T1003: 1
A1004: P1003 | B1004: Packaged Food | C1004: Alimentos y bebidas | D1004: Pedigree Puppy Chicken Chunks in Gravy | E1004: 35 | F1004: 2 | G1004: 34 | H1004: =ROUND(E1004-G1004,2) -> 1 | I1004: 0 | J1004: =TRUE() -> TRUE | K1004: =IF(J1004,1,0) -> 1 | L1004: Agotado | M1004: =ROUND(G1004*I1004,2) -> 0 | N1004: =ROUND(H1004*I1004,2) -> 0 | O1004: 70 | P1004: 70 | Q1004: 0-50 | R1004: 1-10% | S1004: 3 | T1004: 1
A1005: P1004 | B1005: Packaged Food | C1005: Alimentos y bebidas | D1005: Lijjat Moong Papad | E1005: 60 | F1005: 5 | G1005: 57 | H1005: =ROUND(E1005-G1005,2) -> 3 | I1005: 0 | J1005: =TRUE() -> TRUE | K1005: =IF(J1005,1,0) -> 1 | L1005: Agotado | M1005: =ROUND(G1005*I1005,2) -> 0 | N1005: =ROUND(H1005*I1005,2) -> 0 | O1005: 200 | P1005: 200 | Q1005: 51-100 | R1005: 1-10% | S1005: 3 | T1005: 1
A1006: P1005 | B1006: Packaged Food | C1006: Alimentos y bebidas | D1006: Mothers Recipe Papad - Sabudana With Rock Salt | E1006: 31 | F1006: 9 | G1006: 28 | H1006: =ROUND(E1006-G1006,2) -> 3 | I1006: 0 | J1006: =TRUE() -> TRUE | K1006: =IF(J1006,1,0) -> 1 | L1006: Agotado | M1006: =ROUND(G1006*I1006,2) -> 0 | N1006: =ROUND(H1006*I1006,2) -> 0 | O1006: 70 | P1006: 70 | Q1006: 0-50 | R1006: 1-10% | S1006: 3 | T1006: 1
A1007: P1006 | B1007: Packaged Food | C1007: Alimentos y bebidas | D1007: Veeba Favourites Eggless Burger Mayonnaise | E1007: 69 | F1007: 8 | G1007: 63 | H1007: =ROUND(E1007-G1007,2) -> 6 | I1007: 0 | J1007: =TRUE() -> TRUE | K1007: =IF(J1007,1,0) -> 1 | L1007: Agotado | M1007: =ROUND(G1007*I1007,2) -> 0 | N1007: =ROUND(H1007*I1007,2) -> 0 | O1007: 250 | P1007: 250 | Q1007: 51-100 | R1007: 1-10% | S1007: 3 | T1007: 1
A1008: P1007 | B1008: Packaged Food | C1008: Alimentos y bebidas | D1008: Kelloggs Corn Flakes With Real Strawberry Pure | E1008: 265 | F1008: 10 | G1008: 236 | H1008: =ROUND(E1008-G1008,2) -> 29 | I1008: 0 | J1008: =TRUE() -> TRUE | K1008: =IF(J1008,1,0) -> 1 | L1008: Agotado | M1008: =ROUND(G1008*I1008,2) -> 0 | N1008: =ROUND(H1008*I1008,2) -> 0 | O1008: 575 | P1008: 575 | Q1008: 201-500 | R1008: 1-10% | S1008: 3 | T1008: 1
A1009: P1008 | B1009: Packaged Food | C1009: Alimentos y bebidas | D1009: Mother's Recipe Potato Papad | E1009: 31 | F1009: 9 | G1009: 28 | H1009: =ROUND(E1009-G1009,2) -> 3 | I1009: 0 | J1009: =TRUE() -> TRUE | K1009: =IF(J1009,1,0) -> 1 | L1009: Agotado | M1009: =ROUND(G1009*I1009,2) -> 0 | N1009: =ROUND(H1009*I1009,2) -> 0 | O1009: 70 | P1009: 75 | Q1009: 0-50 | R1009: 1-10% | S1009: 3 | T1009: 1
... A1024: P1023 | B1024: Packaged Food | C1024: Alimentos y bebidas | D1024: Del Monte Pitted Green Olives | E1024: 250 | F1024: 0 | G1024: 250 | H1024: =ROUND(E1024-G1024,2) -> 0 | I1024: 0 | J1024: =TRUE() -> TRUE | K1024: =IF(J1024,1,0) -> 1 | L1024: Agotado | M1024: =ROUND(G1024*I1024,2) -> 0 | N1024: =ROUND(H1024*I1024,2) -> 0 | O1024: 450 | P1024: 450 | Q1024: 201-500 | R1024: Sin descuento | S1024: 3 | T1024: 1
A1025: P1024 | B1025: Meats, Fish & Eggs | C1025: Alimentos y bebidas | D1025: Godrej Real Good Chicken Whole Pre-Cut | E1025: 300 | F1025: 10 | G1025: 270 | H1025: =ROUND(E1025-G1025,2) -> 30 | I1025: 4 | J1025: =FALSE() -> FALSE | K1025: =IF(J1025,1,0) -> 0 | L1025: Medio (3-5) | M1025: =ROUND(G1025*I1025,2) -> 1080 | N1025: =ROUND(H1025*I1025,2) -> 120 | O1025: 1000 | P1025: 1 | Q1025: 201-500 | R1025: 1-10% | S1025: 1 | T1025: 1
...

Sheet estadisticas
A1: Estadística descriptiva y valores de referencia
A2: Calculada con fórmulas sobre la hoja 'productos_unicos' (1 fila por producto, sin contar dos veces los productos listados en varias categorías). Desviación estándar muestral (STDEV).
A4: Variable | B4: Unidad | C4: n | D4: Media | E4: Mediana | F4: Moda | G4: Desv. estándar | H4: Mínimo | I4: Máximo | J4: Coef. variación
A5: precio_lista | B5: rupias | C5: =COUNT(productos_unicos!$E$2:$E$1801) -> 1800 | D5: =AVERAGE(productos_unicos!$E$2:$E$1801) -> 153.15889 | E5: =MEDIAN(productos_unicos!$E$2:$E$1801) -> 105 | F5: =IFERROR(MODE(productos_unicos!$E$2:$E$1801),"sin moda") -> 60 | G5: =STDEV(productos_unicos!$E$2:$E$1801) -> 162.71136 | H5: =MIN(productos_unicos!$E$2:$E$1801) -> 10 | I5: =MAX(productos_unicos!$E$2:$E$1801) -> 2600 | J5: =IF(D5=0,0,G5/D5) -> 1.0623697
A6: precio_venta | B6: rupias | C6: =COUNT(productos_unicos!$G$2:$G$1801) -> 1800 | D6: =AVERAGE(productos_unicos!$G$2:$G$1801) -> 138.66311 | E6: =MEDIAN(productos_unicos!$G$2:$G$1801) -> 99 | F6: =IFERROR(MODE(productos_unicos!$G$2:$G$1801),"sin moda") -> 25 | G6: =STDEV(productos_unicos!$G$2:$G$1801) -> 139.65628 | H6: =MIN(productos_unicos!$G$2:$G$1801) -> 9 | I6: =MAX(productos_unicos!$G$2:$G$1801) -> 1399 | J6: =IF(D6=0,0,G6/D6) -> 1.0071624
A7: descuento_pct | B7: % | C7: =COUNT(productos_unicos!$F$2:$F$1801) -> 1800 | D7: =AVERAGE(productos_unicos!$F$2:$F$1801) -> 7.7233333 | E7: =MEDIAN(productos_unicos!$F$2:$F$1801) -> 6 | F7: =IFERROR(MODE(productos_unicos!$F$2:$F$1801),"sin moda") -> 0 | G7: =STDEV(productos_unicos!$F$2:$F$1801) -> 8.8442838 | H7: =MIN(productos_unicos!$F$2:$F$1801) -> 0 | I7: =MAX(productos_unicos!$F$2:$F$1801) -> 51 | J7: =IF(D7=0,0,G7/D7) -> 1.1451382
A8: ahorro_unitario | B8: rupias | C8: =COUNT(productos_unicos!$H$2:$H$1801) -> 1800 | D8: =AVERAGE(productos_unicos!$H$2:$H$1801) -> 14.495778 | E8: =MEDIAN(productos_unicos!$H$2:$H$1801) -> 6 | F8: =IFERROR(MODE(productos_unicos!$H$2:$H$1801),"sin moda") -> 0 | G8: =STDEV(productos_unicos!$H$2:$H$1801) -> 40.685775 | H8: =MIN(productos_unicos!$H$2:$H$1801) -> 0 | I8: =MAX(productos_unicos!$H$2:$H$1801) -> 1201 | J8: =IF(D8=0,0,G8/D8) -> 2.8067328
A9: cantidad_disponible | B9: unidades | C9: =COUNT(productos_unicos!$I$2:$I$1801) -> 1800 | D9: =AVERAGE(productos_unicos!$I$2:$I$1801) -> 3.9977778 | E9: =MEDIAN(productos_unicos!$I$2:$I$1801) -> 5 | F9: =IFERROR(MODE(productos_unicos!$I$2:$I$1801),"sin moda") -> 6 | G9: =STDEV(productos_unicos!$I$2:$I$1801) -> 2.196818 | H9: =MIN(productos_unicos!$I$2:$I$1801) -> 0 | I9: =MAX(productos_unicos!$I$2:$I$1801) -> 6 | J9: =IF(D9=0,0,G9/D9) -> 0.54950979
A10: valor_inventario | B10: rupias | C10: =COUNT(productos_unicos!$M$2:$M$1801) -> 1800 | D10: =AVERAGE(productos_unicos!$M$2:$M$1801) -> 588.02978 | E10: =MEDIAN(productos_unicos!$M$2:$M$1801) -> 378 | F10: =IFERROR(MODE(productos_unicos!$M$2:$M$1801),"sin moda") -> 0 | G10: =STDEV(productos_unicos!$M$2:$M$1801) -> 747.98575 | H10: =MIN(productos_unicos!$M$2:$M$1801) -> 0 | I10: =MAX(productos_unicos!$M$2:$M$1801) -> 8394 | J10: =IF(D10=0,0,G10/D10) -> 1.2720202
A11: peso_gramos | B11: gramos | C11: =COUNT(productos_unicos!$O$2:$O$1801) -> 1798 | D11: =AVERAGE(productos_unicos!$O$2:$O$1801) -> 389.26029 | E11: =MEDIAN(productos_unicos!$O$2:$O$1801) -> 200 | F11: =IFERROR(MODE(productos_unicos!$O$2:$O$1801),"sin moda") -> 200 | G11: =STDEV(productos_unicos!$O$2:$O$1801) -> 701.20109 | H11: =MIN(productos_unicos!$O$2:$O$1801) -> 1 | I11: =MAX(productos_unicos!$O$2:$O$1801) -> 10000 | J11: =IF(D11=0,0,G11/D11) -> 1.8013682
A12: cantidad_paquete | B12: según producto | C12: =COUNT(productos_unicos!$P$2:$P$1801) -> 1797 | D12: =AVERAGE(productos_unicos!$P$2:$P$1801) -> 201.55036 | E12: =MEDIAN(productos_unicos!$P$2:$P$1801) -> 150 | F12: =IFERROR(MODE(productos_unicos!$P$2:$P$1801),"sin moda") -> 200 | G12: =STDEV(productos_unicos!$P$2:$P$1801) -> 196.66168 | H12: =MIN(productos_unicos!$P$2:$P$1801) -> 1 | I12: =MAX(productos_unicos!$P$2:$P$1801) -> 1500 | J12: =IF(D12=0,0,G12/D12) -> 0.97574459
A14: Valores de referencia para validar las medidas de Power BI
A15: Indicador | B15: Valor | C15: Cómo se calcula
A16: Filas en datos_limpios (listados) | B16: =COUNTA(datos_limpios!A2:A3730) -> 3729 | C16: Un producto aparece una vez por categoría en la que está listado
A17: Productos únicos | B17: =COUNTA(productos_unicos!A2:A1801) -> 1800 | C17: Filas con es_listado_principal = 1
A18: Valor de inventario, solo únicos (₹) | B18: =SUM(productos_unicos!M2:M1801) -> 1058453.6 | C18: Cifra correcta para el total del inventario
A19: Valor de inventario, todos los listados (₹) | B19: =SUM(datos_limpios!M2:M3730) -> 2241460.6 | C19: Cuenta dos o más veces los productos repetidos; no usar como total
A20: % de productos agotados (únicos) | B20: =AVERAGE(productos_unicos!K2:K1801) -> 0.12055556 | C20: Productos con cantidad_disponible = 0
A21: Descuento promedio (únicos, %) | B21: =AVERAGE(productos_unicos!F2:F1801) -> 7.7233333 | C21: Promedio simple de descuento_pct
A22: Ahorro potencial total, únicos (₹) | B22: =SUM(productos_unicos!N2:N1801) -> 115512.4 | C22: Σ (precio_lista − precio_venta) × cantidad_disponible
A23: Total de datos en datos_limpios | B23: =COUNTA(datos_limpios!A2:A3730)*20 -> 74580 | C23: Filas × 20 columnas (valores vacíos incluidos)

Sheet diccionario
A1: Diccionario de datos
A3: Columna | B3: Tipo | C3: Unidad | D3: Descripción | E3: Origen
A4: id_producto | B4: texto | C4: — | D4: Identificador creado por nosotros (el dataset original no trae ID). Dos filas con el mismo nombre, precios, descuento, stock, peso y paquete comparten ID. | E4: Nueva
A5: categoria | B5: texto | C5: — | D5: Categoría de la tienda (14 categorías). Original: Category. | E5: Original (renombrada)
A6: grupo | B6: texto | C6: — | D6: Agrupación de las 14 categorías en 3 grupos. SUPUESTO nuestro: Paan Corner se ubica en Cuidado personal y salud porque su lista de productos es idéntica a la de Personal Care. | E6: Nueva
A7: producto | B7: texto | C7: — | D7: Nombre del producto, sin espacios sobrantes. Original: name. | E7: Original (renombrada)
A8: precio_lista | B8: número | C8: rupias (₹) | D8: Precio máximo de venta (MRP). Original: mrp ÷ 100. SUPUESTO: el original viene en paise (centésimas de rupia); confirmar en la descripción del dataset en Kaggle. | E8: Original (÷100)
A9: descuento_pct | B9: entero | C9: % (0–100) | D9: Porcentaje de descuento. Original: discountPercent. | E9: Original (renombrada)
A10: precio_venta | B10: número | C10: rupias (₹) | D10: Precio con descuento. Original: discountedSellingPrice ÷ 100. | E10: Original (÷100)
A11: ahorro_unitario | B11: número | C11: rupias (₹) | D11: Fórmula: precio_lista − precio_venta. | E11: Nueva
A12: cantidad_disponible | B12: entero | C12: unidades | D12: Unidades disponibles. Original: availableQuantity. El máximo observado es 6 y es el valor más frecuente, por lo que probablemente está topado; valor_inventario es un indicador relativo, no el valor real del stock. | E12: Original (renombrada)
A13: agotado | B13: lógico | C13: VERDADERO/FALSO | D13: Original: outOfStock. Coincide exactamente con cantidad_disponible = 0. | E13: Original (renombrada)
A14: agotado_num | B14: entero | C14: 0/1 | D14: Fórmula: 1 si agotado, 0 si no. Facilita medidas DAX y promedios. | E14: Nueva
... A23: es_listado_principal | B23: entero | C23: 0/1 | D23: 1 en la primera aparición de cada id_producto. Filtrar por 1 para totales sin duplicar productos. | E23: Nueva

Sheet limpieza
A1: Registro de limpieza
A3: Paso | B3: Qué se hizo | C3: Filas o valores afectados | D3: Filas restantes
A4: 0. Carga | B4: Filas y columnas originales | C4: 3732 | D4: 3732
A5: 1. Texto | B5: Nombres con espacios sobrantes corregidos (categoria y producto) | C5: 337 | D5: 3732
A6: 2. Duplicados | B6: Filas identicas en todas las columnas eliminadas | C6: 2 | D6: 3730
A7: 3. Precios | B7: Filas con precio de lista o de venta en 0 eliminadas | C7: 1 | D7: 3729
A8: 4. Ceros invalidos | B8: peso_gramos = 0 convertido a vacio | C8: 4 | D8: 3729
A9: 4. Ceros invalidos | B9: cantidad_paquete = 0 convertido a vacio | C9: 6 | D9: 3729
A10: 5. Unidades | B10: precio_lista y precio_venta divididos entre 100 (paise a rupias) | C10: 3729 | D10: 3729
A11: 6. Identificador | B11: Productos unicos detectados (id_producto) | C11: 1800 | D11: 3729
A12: 6. Identificador | B12: Productos listados en 2 o mas categorias | C12: 1281 | D12: 3729
A13: 7. Derivadas | B13: Columnas nuevas agregadas | C13: 11 | D13: 3729
A15: Hallazgos que afectan el análisis
A16: Listas repetidas entre categorías: Cooking Essentials = Munchies (514 filas), Chocolates & Candies = Ice Cream & Desserts = Packaged Food (388), Paan Corner = Personal Care (343) y Beverages = Dairy, Bread & Batter (129) contienen los mismos productos con los mismos valores.
A17: Por eso hay 3,729 filas pero solo 1,800 productos únicos. Sumar sobre todas las filas más que duplica el valor del inventario; para totales usar es_listado_principal = 1.
A18: No hay columna de fecha: no se pueden hacer tendencias en el tiempo con este dataset.
A19: cantidad_disponible parece topado en 6 unidades; el valor de inventario es un indicador relativo.
A20: Los ceros en descuento_pct (1,177 filas) son válidos: productos sin descuento.
A21: Los vacíos en peso_gramos y cantidad_paquete se conservaron como vacíos para no inventar datos; los promedios los ignoran.
